Workbook

Sheet Resumen
A1: MÓDULOS | B1: OBJETIVOS | C1: NUM ACT | D1: ACTIVIDAD | E1: FEEDBACK | F1: CONCLUSIÓN | G1: CONTENIDOS
A2: ='Cont-Obj'!A:A -> Módulo 1. La seguridad alimentaria empieza contigo | B2: ='Cont-Obj'!B:B -> O1.1 Conocer la definición de manipulador de alimentos | C2: ='Cont-Obj'!C:C -> 1 | D2: {=IF(C2:C1001="","",IFERROR(VLOOKUP(C2:C1001,'Actividades de aprendizaje'!A:E,{2,3,4},FALSE),""))} -> Mesa del comedor | E2: Actividad de lectura: ¿Qué es un manipulador de alimentos? Enunciado: Antes de empezar a moverte por el restaurante, hay algo que debes tener claro: qué significa ser manipulador de alimentos. Tranquilo, es más sencillo de lo que parece: Un manipulador de alimentos es cualquier persona que, por su trabajo, entra en contacto con alimentos o realiza tareas que pueden influir en su seguridad. Fíjate en la última parte: 'cualquier persona que... realiza tareas que pueden influir en su seguridad'. Eso incluye a mucha más gente de la que parece. De hecho, ahora mismo voy a ponerte a prueba con algunos ejemplos. ¿Preparado?" | G2: ='Cont-Obj'!E:E -> 1.1 ¿Qué es un manipulador de alimentos?
A3: ='Cont-Obj'!A:A -> Módulo 1. La seguridad alimentaria empieza contigo | B3: ='Cont-Obj'!B:B -> O1.2 Identificar qué puestos de trabajo implican manipulación de alimentos dentro de la cadena alimentaria. | C3: ='Cont-Obj'!C:C -> 2 | D3: Mesa del comedor (vista desde arriba) | E3: Título de la actividad: ¿Quién es manipulador de alimentos? Enunciado: No todos los manipuladores de alimentos son cocineros. En esta actividad vas a conocer a distintas personas y sus puestos de trabajo. Lee con atención su carnet: su nombre, su oficio y lo que hace en su día a día. Tu misión es decidir si su trabajo implica manipular alimentos: 👉 Desliza la tarjeta a la derecha si crees que SÍ es manipulador de alimentos. 👈 Desliza la tarjeta a la izquierda si crees que NO lo es. ¡Adelante, detective!" Descripción: En el centro de la pantalla aparecerá una tarjeta con formato de carnet de identidad. Incluirá una ilustración de la persona de cabeza a pecho, vestida con su uniforme, y a la izquierda su nombre, puesto de trabajo y una breve descripción de sus funciones. El alumno deberá hacer swipe a la derecha si considera que es manipulador de alimentos y a la izquierda si considera que no. Personajes / tarjetas (Nombre, puesto y descripción): - Óscar Fernández: Cocinero del restaurante El Caserío. Me encargo de preparar los platos de la carta para que los clientes queden satisfechos. - Laura Martín: Camarera de la cafetería La plaza. Sirvo los platos y las bebidas. Además atiendo a los clientes en la sala. - Pablo Sánchez: Personal de cafetería. Preparo cafés, bebidas y otros productos que se sirven a los clientes. - Marta López: Transportista de la frutería Hermanos López. Reparto la mercancía a los restaurantes de la zona. - Miguel Rodríguez: Repartidor de la pizzería Primavera. Llevo en moto los pedidos a domicilio. - Javier Ruiz: Mozo de almacen de Supermercados Luna. Recibo las mercancías, compruebo los productos y los coloco en las zonas de almacenamiento correspondientes. - Ana García: Dependienta de la carnicería Loli. Atiendo a los clientes, preparo y entrego los productos cárnicos que solicitan. - Sonia Moreno: Operaria de envasado. Empaqueto y etiqueto comida preparada en envases herméticos. - Carmen Díaz: Personal de limpieza. Me encargo de mantener limpias las oficinas y las zonas comunes del edificio. - Sergio Navarro: Comercial de Homesec. Visito establecimientos para presentar nuestros productos y explicar sus características a los clientes. - Elena Torres: Recepcionista de hotel Gold. Recibo a los clientes, gestiono sus entradas y salidas y atiendo sus consultas. Respuesta correcta: Los ocho primeros son manipuladores de alimentos. Los tres últimos no lo son. | F3: El feedback será específico para cada personaje, pero mantendrá la misma estructura tanto para respuestas correctas como incorrectas: Si es manipulador: - ¡Correcto!/¡Incorrecto! Óscar es manipulador de alimentos porque, como cocinero, está en contacto directo con los alimentos durante su preparación. - ¡Correcto!/¡Incorrecto! Laura es manipuladora de alimentos porque, como camarera tiene contacto con los alimentos durante el servicio de los mismos. - ¡Correcto!/¡Incorrecto! Pablo es manipulador de alimentos porque, como personal de cafetería, prepara y sirve cafés, bebidas y otros productos que van destinados directamente al consumo de los clientes. - ¡Correcto!/¡Incorrecto! Marta es manipuladora de alimentos porque, como transportista de una frutería, traslada mercancías alimentarias y debe garantizar que se mantengan en condiciones adecuadas hasta su entrega a los restaurantes. - ¡Correcto!/¡Incorrecto! Miguel es manipulador de alimentos porque, como repartidor de una pizzería, transporta los pedidos de comida hasta el domicilio de los clientes, velando por que lleguen en buen estado. - ¡Correcto!/¡Incorrecto! Javier es manipulador de alimentos porque, como mozo de almacén de un supermercado, recibe, comprueba y coloca productos alimentarios en las zonas de almacenamiento correspondientes. - ¡Correcto!/¡Incorrecto! Ana es manipuladora de alimentos porque, como dependienta de una carnicería, prepara y entrega directamente a los clientes los productos cárnicos que solicitan. - ¡Correcto!/¡Incorrecto! Sonia es manipuladora de alimentos porque, como operaria de envasado, empaqueta y etiqueta comida preparada en envases herméticos, estando en contacto directo con los alimentos. Si no es manipulador: - ¡Correcto!/¡Incorrecto! Carmen no es manipuladora de alimentos porque realiza tareas de limpieza en oficinas y zonas comunes que no están relacionadas con la manipulación de alimentos ni con superficies destinadas a ellos. - ¡Correcto!/¡Incorrecto! Sergio no es manipulador de alimentos porque sus funciones se limitan a presentar productos de un sector que no interviene en ninguna tarea relacionada con los alimentos. - ¡Correcto!/¡Incorrecto! Elena no es manipuladora de alimentos porque sus funciones se limitan a la recepción y atención de clientes y no interviene en ninguna tarea relacionada con los alimentos. | G3: ='Cont-Obj'!E:E -> 1.1 ¿Qué es un manipulador de alimentos?
A4: ='Cont-Obj'!A:A -> Módulo 1. La seguridad alimentaria empieza contigo | B4: ='Cont-Obj'!B:B -> O1.3 Comprender la importancia del papel del manipulador de alimentos en la seguridad y salud de los consumidores. | C4: ='Cont-Obj'!C:C -> 3 | D4: Recepción (tablet) | E4: Título de la actividad: Cámaras de seguridad: del manipulador al consumidor. Enunciado: Bienvenido/a al sistema de videovigilancia del restaurante. Observa las grabaciones de la cámara de seguridad. Tu misión es decidir si lo que ves supone un riesgo para la seguridad alimentaria y averiguar por qué es importante la actuación del manipulador de alimentos. En algunos casos, tendrás que ir más allá y detectar qué consecuencias podría tener cada situación para el consumidor. Analiza cada escena como si fueras el responsable de seguridad alimentaria del local. ¡Adelante! Descripción: Actividad interactiva de análisis causa-efecto. El alumnado visualiza una galería de vídeos que simulan las cámaras de seguridad de un establecimiento de hostelería. Para cada grabación debe: (1) decidir si la situación supone un riesgo para la seguridad alimentaria; (2) si hay riesgo, identificar por qué es importante la actuación del manipulador; y (3) en varios casos, determinar qué consecuencia podría tener esa situación para el consumidor. Se trabaja la relación actuación del manipulador → efecto sobre el alimento → posible consecuencia para el consumidor, más allá de la simple identificación de buenas y malas prácticas. Situaciones que se visualizan en los vídeos: Vídeo 1: En la cocina, un cocinero coge tomates para cortarlos y ensalzarlos, pero no se ha lavado las manos previamente. Pregunta 1. ¿Supone un riesgo para la seguridad alimentaria? ✅ Sí No Pregunta 2. ¿Por qué es importante que el manipulador se lave las manos antes de manipular los alimentos? ✅ A. Porque puede transferir microorganismos al alimento. ❌ B. Porque los alimentos tendrán mejor aspecto. ❌ C. Porque terminará antes la preparación. ❌D. Porque evitará que el alimento se enfríe. Vídeo 2: Una cocinera corta pollo crudo y utiliza una tabla y un cuchillo limpios, específicos para ese uso. Pregunta 1. ¿Supone un riesgo para la seguridad alimentaria? Sí ✅ No (Al ser una práctica correcta, no avanza a más preguntas. Se pasa al siguiente vídeo con feedback positivo.) Vídeo 3: Un ayudante de cocina utiliza un cuchillo y una tabla que tienen restos de comida seca de usos anteriores para trocear verduras. Pregunta 1. ¿Supone un riesgo para la seguridad alimentaria? ✅ Sí No Pregunta 2. ¿Por qué es importante utilizar utensilios limpios durante la preparación de los alimentos? ✅ A. Porque los restos y microorganismos de usos anteriores pueden pasar al alimento. ❌ B. Porque es suficiente retirar los restos de comida antes de utilizar de nuevo los utensilios. ❌ C. Porque los utensilios deben limpiarse al terminar el servicio, aunque se utilicen con distintos alimentos durante la preparación. ❌ D. Porque basta con utilizar utensilios diferentes para cada alimento, aunque no se hayan limpiado previamente. Vídeo 4: Un trabajador saca un recipiente con mayonesa casera de la nevera y lo deja encima de la encimera durante horas mientras prepara otras tareas, a temperatura ambiente. Pregunta 1. ¿Supone un riesgo para la seguridad alimentaria? ✅ Sí No Pregunta 2. ¿Por qué es importante mantener los alimentos perecederos a temperatura segura? ✅ A. Porque a temperatura ambiente los microorganismos pueden multiplicarse rápidamente en el alimento. ❌ B. Porque es suficiente mantener el alimento refrigerado hasta el momento de empezar a prepararlo. ❌ C. Porque mantener el alimento tapado permite dejarlo fuera de la nevera mientras se realizan otras tareas. ❌ D. Porque la temperatura solo necesita controlarse cuando el alimento va a conservarse hasta el día siguiente.Pregunta 3. ¿Qué consecuencia podría tener esta situación para el consumidor? Pregunta 3. ¿Qué consecuencia podría tener esta situación para el consumidor? ✅ A. Que el alimento pueda contener microorganismos capaces de causar una enfermedad alimentaria. ❌ B. Que el alimento se deteriore antes, pero sin que ello suponga necesariamente un riesgo para el consumidor. ❌ C. Que el alimento conserve sus condiciones de seguridad siempre que se refrigere antes de servirlo. ❌ D. Que el alimento solo represente un riesgo si presenta cambios visibles en su aspecto u olor. Vídeo 5: En la cámara frigorífica, se ve cómo un cocinero comprueba con un termómetro que los lácteos y las carnes están a la temperatura establecida y anota el registro. Pregunta 1. ¿Supone un riesgo para la seguridad alimentaria? Sí ✅ No (Práctica correcta: no avanza a más preguntas.) Vídeo 6: Un manipulador coloca pechugas de pollo crudas en la misma bandeja donde hay lechuga ya lavada y lista para servir. Pregunta 1. ¿Supone un riesgo para la seguridad alimentaria? ✅ Sí No Pregunta 2. ¿Por qué es importante separar los alimentos crudos de los listos para consumir? ✅ A. Porque los microorganismos del pollo crudo pueden pasar a la lechuga. ❌ B. Porque los alimentos crudos deben mantenerse separados únicamente durante su almacenamiento en la cámara frigorífica. ❌ C. Porque utilizar una bandeja para cada alimento es suficiente, aunque después se coloquen una junto a otra y entren en contacto. ❌ D. Porque los alimentos listos para consumir solo necesitan separarse de los crudos cuando van a servirse sin lavar. Pregunta 3. ¿Qué consecuencia podría tener esta situación para el consumidor? ✅ A. Que la lechuga se contamine y transmita microorganismos al consumidor al ingerirla. ❌ B. Que el pollo necesite cocinarse durante más tiempo para compensar el contacto con la lechuga. ❌ C. Que la lechuga pierda frescura durante su conservación, aunque no se vea afectada su seguridad alimentaria. ❌ D. Que sea suficiente retirar las hojas que han estado en contacto directo con el pollo para eliminar el riesgo. Vídeo 7: En la zona de preparación, un cocinero tiene en una bandeja la carne cruda y, en otra separada, los vegetales listos para consumir. Pregunta 1. ¿Supone un riesgo para la seguridad alimentaria? Sí ✅ No (Práctica correcta: no avanza a más preguntas.) Vídeo 8: Un trabajador consulta la ficha de procedimiento del local, se coloca el gorro y los guantes limpios y sigue los pasos indicados para manipular un alimento. Pregunta 1. ¿Supone un riesgo para la seguridad alimentaria? Sí ✅ No (Práctica correcta: no avanza a más preguntas.) | F4: Feedback de la Pregunta 1 (¿Supone un riesgo?): Acierto: ¡Correcto! Has identificado bien si la situación supone o no un riesgo para la seguridad alimentaria. Error: Revisa la escena con calma. ¿La actuación del manipulador puede contaminar el alimento? ¿O se trata de una práctica segura? Recuerda: los riesgos no siempre se ven a simple vista. Feedback de la Pregunta 2 (¿Por qué es importante?): Acierto: ¡Exacto! Has entendido por qué la actuación del manipulador afecta directamente a la seguridad del alimento. Error: Vuelve a pensarlo: la actuación del manipulador no es una formalidad, tiene un efecto real sobre el alimento. ¿Qué puede pasarle al alimento si esa actuación es incorrecta? Feedback de la Pregunta 3 (¿Qué consecuencia para el consumidor?): Acierto: ¡Perfecto! Has llegado hasta el final de la cadena: la actuación del manipulador puede acabar afectando a la salud del consumidor. Error: Recuerda la cadena completa: actuación incorrecta del manipulador → contaminación del alimento → riesgo para el consumidor. ¿Cuál de las opciones refleja ese efecto real sobre la salud? | G4: ='Cont-Obj'!E:E -> 1.2 ¿Por qué es tan importante tu trabajo?
A5: ='Cont-Obj'!A:A -> Módulo 1. La seguridad alimentaria empieza contigo | B5: ='Cont-Obj'!B:B -> O1.4 Reconocer las principales consecuencias que puede tener una manipulación incorrecta de los alimentos para los consumidores, el establecimiento y el propio manipulador. | C5: ='Cont-Obj'!C:C -> 4 | D5: Recepción (Actividad oral: David te narra situaciones, debes contestar pulsando botones: Consumidor, Establecimiento y Manipulador) | E5: Título de la actividad: ¿A quién afecta? Enunciado: Cuando un alimento no se manipula correctamente, las consecuencias no afectan solo a una parte. Detrás de cada error hay personas, negocios y profesionales que pueden salir perjudicados. En pantalla irán apareciendo diferentes consecuencias. Tu tarea es arrastrar cada una al cajón correcto según a quién afecta principalmente: 🧑 Consumidor → si la consecuencia recae sobre la salud o la experiencia de quien consume el alimento. 🏪 Establecimiento → si la consecuencia afecta al negocio, su funcionamiento o su economía. 👨‍🍳 Manipulador → si la consecuencia recae sobre el propio trabajador que manipula los alimentos. Lee bien cada tarjeta antes de arrastrarla: algunas pueden parecer similares, pero el impacto principal marca la diferencia. ¡Coloca cada consecuencia en su cajón! Descripción: Actividad interactiva de clasificación por arrastre (drag and drop). En el centro de la pantalla van apareciendo, una a una, distintas consecuencias derivadas de una manipulación incorrecta de los alimentos. El alumnado debe arrastrar cada consecuencia al cajón correspondiente según quién se ve afectado: Consumidor, Establecimiento o Manipulador. Se trabajan los tres ámbitos de impacto de la seguridad alimentaria: salud, negocio y responsabilidad profesional. Consecuencias a clasificar: - Un cliente enferma después de consumir un alimento contaminado. → Consumidor - Un cliente tiene que recibir atención médica después de consumir un alimento contaminado. → Consumidor - Una persona alérgica sufre una reacción grave por una gestión incorrecta de un alérgeno. → Consumidor - El establecimiento recibe quejas y reclamaciones de los clientes. → Establecimiento - Se producen devoluciones o es necesario retirar productos. → Establecimiento - Se desperdician alimentos como consecuencia de un problema de seguridad alimentaria. → Establecimiento - Un cliente pierde la confianza en el establecimiento después de sufrir un problema relacionado con un alimento. → Establecimiento - El negocio recibe una inspección o una sanción. → Establecimiento - El trabajador puede recibir una sanción laboral por incumplir los procedimientos de seguridad alimentaria. → Manipulador - El trabajador puede enfermar al entrar en contacto con alimentos contaminados durante una manipulación incorrecta. → Manipulador | F5: Respuestas correctas: - Consumidor: ¡Correcto! Cuando la consecuencia recae sobre la salud o la seguridad de quien consume el alimento, estamos ante un impacto directo en el consumidor. Enfermedades, intoxicaciones o reacciones alérgicas graves son las consecuencias más serias de una mala manipulación. - Establecimiento: ¡Muy bien! Quejas, devoluciones, retirada de productos, desperdicio de alimentos, pérdidas económicas, inspecciones o sanciones afectan directamente al negocio y a su reputación. - Manipulador: ¡Exacto! El trabajador que ignora los procedimientos puede enfrentarse a consecuencias laborales y, en casos graves, a responsabilidades administrativas, civiles o incluso penales. Respuestas incorrectas: - Si has arrastrado la tarjeta al cajón "Consumidor" y no correspondía: Cuidado: no todas las consecuencias graves afectan al consumidor. Si la tarjeta hablaba de sanciones, pérdidas, quejas o responsabilidades del trabajador, el afectado no es quien consume el alimento. Pregúntate de nuevo: ¿quién sufre directamente esta consecuencia? - Si has arrastrado la tarjeta al cajón "Establecimiento" y no correspondía: Cuidado: no todo lo que ocurre en el local afecta al negocio como tal. Si la tarjeta hablaba de enfermedades, reacciones alérgicas o responsabilidades del trabajador, el afectado no es el establecimiento. Pregúntate de nuevo: ¿quién sufre directamente esta consecuencia? - Si has arrastrado la tarjeta al cajón "Manipulador" y no correspondía: Cuidado: no todas las consecuencias recaen sobre el trabajador. Si la tarjeta hablaba de enfermedades del cliente, quejas, pérdidas económicas o sanciones al negocio, el afectado no es el manipulador. Pregúntate de nuevo: ¿quién sufre directamente esta consecuencia? | G5: ='Cont-Obj'!E:E -> 1.3 ¿Qué puede ocurrir si no manipulamos bien los alimentos?
A6: ='Cont-Obj'!A:A -> Módulo 1. La seguridad alimentaria empieza contigo | B6: ='Cont-Obj'!B:B -> O1.5 Identificar las reglas básicas de seguridad alimentaria durante las tareas de manipulación. | C6: ='Cont-Obj'!C:C -> 5 | D6: Recepción (tablet) | E6: Título de la actividad: Detectives de la cocina: encuentra las 8 reglas básicas. Enunciado: Esta cocina tiene un problema: en algún punto de la imagen se está incumpliendo cada una de las 8 reglas básicas para trabajar con seguridad alimentaria. A la izquierda tienes las 8 reglas. Pasa el ratón por la imagen para descubrir los puntos calientes y arrastra cada regla hasta el punto donde creas que se está incumpliendo. Fíjate bien en todos los detalles de la imagen. ¡Demuestra que sabes leer una cocina como un profesional!" Descripción: Actividad de emparejamiento por arrastre. A la izquierda de la pantalla aparecen las 8 reglas básicas para trabajar con seguridad alimentaria y a la derecha se muestra una imagen de una cocina profesional con 8 puntos calientes ocultos. El alumnado debe arrastrar cada regla al punto de la imagen donde se está incumpliendo o poniendo en riesgo esa regla concreta. Reglas y punto caliente correcto: Regla --> Punto caliente 1. Mantener una buena higiene personal --> Manos del cocinero sucias. 2. Evitar la contaminación de los alimentos --> Bote de limpieza abierto junto a una caja de zanahorias. 3. Separar los alimentos crudos de los cocinados o listos para consumir --> Bandeja de carne cruda junto a ensalada lista para consumir en la encimera de trabajo. 4. Mantener los alimentos a temperaturas seguras --> Termómetro de nevera marcando 12 °C. 5. Limpiar y desinfectar correctamente los utensilios, equipos e instalaciones --> Cuchillos sucios colocados en su sitio en la pared. 6. Utilizar de forma segura los productos de limpieza --> Producto de limpieza mal cerrado y goteando bajo el fregadero. 7. Gestionar correctamente los alérgenos --> Comanda que especifica "sin huevo" la ensalada preparada en la mesa de trabajo que se visualiza con huevo. 8. Seguir los procedimientos establecidos por el establecimiento. --> Plato cerámica azul con patatas fritas en el pase para salir (en la pared un cartel con los tipos de emplatado, las patatas fritas van en una bandeja metálica) | F6: Feedback por acierto: Regla 1 – ¡Correcto! Las manos sucias del cocinero son el punto donde se incumple esta regla. Una higiene personal deficiente es una de las principales vías de contaminación de los alimentos. Regla 2 – ¡Bien visto! El bote de limpieza abierto junto a los alimentos puede contaminarlos con sustancias químicas. Los productos químicos nunca deben estar cerca de los alimentos. Regla 3 – ¡Exacto! La carne cruda junto a la ensalada lista para consumir es un caso claro de contaminación cruzada. Regla 4 – ¡Muy bien! Un termómetro de nevera marcando 12 °C indica que los alimentos no están a la temperatura segura establecida. La cadena de frío está rota. Regla 5 – ¡Correcto! Unos cuchillos sucios guardados en su sitio no solo incumplen esta regla: pueden contaminar el próximo alimento que se corte con ellos. Regla 6 – ¡Bien detectado! Un producto químico mal cerrado y goteando bajo el fregadero indican un uso y almacenamiento inadecuados de los productos de limpieza. Regla 7 – ¡Exacto! Una comanda que especifica "sin huevo" la ensalada exige una gestión rigurosa del alérgeno: hay que evitar cualquier contacto con el huevo para proteger al cliente. Regla 8 – ¡Correcto! El cartel de emplatado refleja un procedimiento que el manipulador debe conocer y seguir en su trabajo diario. Feedback por error: - Si suelta la regla en un punto ocupado por otra regla: "Ese punto caliente ya está relacionado con otra regla. Fíjate de nuevo en los detalles de la imagen y busca el lugar exacto donde se incumple esta regla." - Si suelta la regla en un punto que no le corresponde: "Casi. Este punto caliente no se corresponde con esta regla. Vuelve a leer la regla y observa con atención qué está ocurriendo en la cocina." | G6: ='Cont-Obj'!E:E -> 1.4 Las reglas básicas para trabajar con seguridad
A7: ='Cont-Obj'!A:A -> Módulo 1. La seguridad alimentaria empieza contigo | B7: ='Cont-Obj'!B:B -> O7.1 Comprender la importancia del trabajo coordinado de todas las personas del establecimiento para garantizar la seguridad alimentaria. | C7: ='Cont-Obj'!C:C | G7: ='Cont-Obj'!E:E -> 1.5 Tu responsabilidad como manipulador de alimentos
A8: ='Cont-Obj'!A:A -> Módulo 2. Higiene personal del manipulador | B8: ='Cont-Obj'!B:B -> O2.1 Conocer las condiciones de salud que pueden afectar a la seguridad de los alimentos. | C8: ='Cont-Obj'!C:C -> 6 | D8: Vestudario (Privado) | E8: Actividad de lectura: Enunciado: | G8: ='Cont-Obj'!E:E -> 2.1 La higiene empieza por ti
A9: ='Cont-Obj'!A:A -> Módulo 2. Higiene personal del manipulador | B9: ='Cont-Obj'!B:B -> O2.1 Conocer las condiciones de salud que pueden afectar a la seguridad de los alimentos. | C9: ='Cont-Obj'!C:C -> 7 | D9: Vestuario (Vista Pared) | E9: Actividad de lectura: Enunciado: | G9: ='Cont-Obj'!E:E -> 2.1 La higiene empieza por ti
A10: ='Cont-Obj'!A:A -> Módulo 2. Higiene personal del manipulador | B10: ='Cont-Obj'!B:B -> O2.2 Aplicar correctamente las normas de higiene personal y utilización del uniforme durante la manipulación de alimentos. | C10: ='Cont-Obj'!C:C -> 8 | D10: Vestuario | E10: Título de la actividad: Antes de comenzar, revisa tu uniforme e higiene. Enunciado: Cuatro compañeros están a punto de empezar su jornada en la cocina. Antes de entrar, hay que revisar que su aspecto sea el adecuado: uniforme completo y limpio, higiene personal correcta y sin objetos que puedan contaminar los alimentos o suponer un riesgo. Observa bien a cada personaje y pulsa sobre todos los elementos que deban modificarse, retirarse o corregirse. ¡No se te puede escapar ni uno! Cuando los tengas todos, ese trabajador estará listo para empezar. Descripción: Actividad interactiva de observación y selección. En el centro de la pantalla aparecen cuatro trabajadores en el vestuario, de frente y vestidos con su uniforme (o con elementos que deben corregir). El alumnado debe pulsar sobre cada elemento de la indumentaria o de la higiene personal que deba modificarse, retirarse o corregirse para poder comenzar la jornada de forma higiénica y segura. Se trabaja la importancia del uniforme limpio, la higiene personal y la correcta utilización de los equipos de protección. Personaje 1 – Hombre con camisa blanca, pantalón negro largo, gorro y zapatos negros apropiados. Elementos a corregir: Barba larga → pulsar para poner redecilla de protección. Uñas sucias → pulsar para limpiar la suciedad bajo las uñas. Móvil en el bolsillo → pulsar el bolsillo para retirarlo. Pendiente largo en la oreja → pulsar la oreja para quitarlo. Personaje 2 – Hombre con camiseta de tirantes blanca, pantalón negro y zapatos apropiados. Elementos a corregir: Camiseta de tirantes → pulsar para cambiarla por la camisa del uniforme. Reloj en la muñeca → pulsar la muñeca para quitarlo. Mancha en el pantalón → pulsar la mancha para eliminarla. Sin gorro → pulsar la cabeza para ponerse el gorro de cocina. Personaje 3 – Mujer con camisa blanca, pantalón negro largo y zapatos apropiados. Elementos a corregir: Pendientes enormes → pulsar las orejas para quitarlos. Brazalete → pulsar la muñeca para quitarlo. Uñas largas → pulsar las manos para cortarlas. Sin gorro → pulsar la cabeza para ponerse el gorro de cocina. Personaje 4 – Mujer con camisa blanca, pantalón negro, gorro de cocina y zapatos de tacón. Elementos a corregir: Pelo suelto → pulsar el pelo para recogerlo. Mal olor en las axilas → pulsar las axilas para corregir la higiene personal. Zapatos de tacón → pulsar los zapatos para sustituirlos por calzado apropiado. Uñas pintadas de rojo → pulsar las manos para retirar el esmalte. | F10: Feedback por acierto: Personaje 1: - Barba larga: ¡Bien! La barba puede acumular microorganismos y restos de comida. Debe cubrirse con una redecilla de protección. - Uñas sucias: ¡Correcto! Las uñas sucias son un foco de contaminación. Hay que mantenerlas cortas y limpias. - Móvil en el bolsillo: ¡Muy bien! El móvil acumula microorganismos y no debe llevarse durante la manipulación de alimentos. - Pendiente largo: ¡Bien visto! Los pendientes grandes pueden caerse y contaminar los alimentos. No deben llevarse durante la jornada. Personaje 2: - Camiseta de tirantes: ¡Correcto! La ropa de calle no sirve como uniforme. Debe usarse la camisa del uniforme, limpia. - Reloj: ¡Bien! El reloj puede acumular suciedad y microorganismos. Debe retirarse antes de manipular alimentos. - Mancha en el pantalón: ¡Muy bien! El uniforme debe estar limpio. Si se mancha, hay que cambiarlo o limpiarlo. - Sin gorro: ¡Correcto! El gorro de cocina es obligatorio para evitar que el pelo caiga en los alimentos. Personaje 3: - Pendientes enormes: ¡Bien! Los pendientes grandes pueden desprenderse y contaminar los alimentos. Deben retirarse. - Brazalete: ¡Correcto! Las joyas acumulan suciedad y pueden caerse. No deben llevarse durante la manipulación. - Uñas largas: ¡Muy bien! Las uñas deben estar cortas y limpias para evitar acumular suciedad y contaminar los alimentos. - Sin gorro: ¡Correcto! El gorro de cocina es obligatorio para evitar que el pelo caiga en los alimentos. Personaje 4: - Pelo suelto: ¡Bien! El pelo debe llevarse recogido y cubierto por el gorro para evitar que caiga en los alimentos. - Mal olor en las axilas: ¡Correcto! La higiene corporal es imprescindible. Una ropa limpia no sustituye una higiene personal adecuada. - Zapatos de tacón: ¡Muy bien! El calzado debe ser apropiado para trabajar: cerrado, cómodo, antideslizante y seguro. - Uñas pintadas: ¡Bien visto! El esmalte puede desprenderse y caer en los alimentos. Las uñas deben llevarse sin pintar, cortas y limpias. Feedback por error: Si pulsa un elemento que no debe corregirse: Ese elemento no supone un problema para la seguridad alimentaria. | G10: ='Cont-Obj'!E:E -> 2.2 El uniforme y la higiene personal
A11: ='Cont-Obj'!A:A -> Módulo 2. Higiene personal del manipulador | B11: ='Cont-Obj'!B:B -> O2.3 Identificar cómo las manos, el cabello, la barba, las uñas, las joyas y la ropa pueden convertirse en fuentes de contaminación. | C11: ='Cont-Obj'!C:C -> 8 | D11: Vestuario | E11: Título de la actividad: Antes de comenzar, revisa tu uniforme e higiene. Enunciado: Cuatro compañeros están a punto de empezar su jornada en la cocina. Antes de entrar, hay que revisar que su aspecto sea el adecuado: uniforme completo y limpio, higiene personal correcta y sin objetos que puedan contaminar los alimentos o suponer un riesgo. Observa bien a cada personaje y pulsa sobre todos los elementos que deban modificarse, retirarse o corregirse. ¡No se te puede escapar ni uno! Cuando los tengas todos, ese trabajador estará listo para empezar. Descripción: Actividad interactiva de observación y selección. En el centro de la pantalla aparecen cuatro trabajadores en el vestuario, de frente y vestidos con su uniforme (o con elementos que deben corregir). El alumnado debe pulsar sobre cada elemento de la indumentaria o de la higiene personal que deba modificarse, retirarse o corregirse para poder comenzar la jornada de forma higiénica y segura. Se trabaja la importancia del uniforme limpio, la higiene personal y la correcta utilización de los equipos de protección. Personaje 1 – Hombre con camisa blanca, pantalón negro largo, gorro y zapatos negros apropiados. Elementos a corregir: Barba larga → pulsar para poner redecilla de protección. Uñas sucias → pulsar para limpiar la suciedad bajo las uñas. Móvil en el bolsillo → pulsar el bolsillo para retirarlo. Pendiente largo en la oreja → pulsar la oreja para quitarlo. Personaje 2 – Hombre con camiseta de tirantes blanca, pantalón negro y zapatos apropiados. Elementos a corregir: Camiseta de tirantes → pulsar para cambiarla por la camisa del uniforme. Reloj en la muñeca → pulsar la muñeca para quitarlo. Mancha en el pantalón → pulsar la mancha para eliminarla. Sin gorro → pulsar la cabeza para ponerse el gorro de cocina. Personaje 3 – Mujer con camisa blanca, pantalón negro largo y zapatos apropiados. Elementos a corregir: Pendientes enormes → pulsar las orejas para quitarlos. Brazalete → pulsar la muñeca para quitarlo. Uñas largas → pulsar las manos para cortarlas. Sin gorro → pulsar la cabeza para ponerse el gorro de cocina. Personaje 4 – Mujer con camisa blanca, pantalón negro, gorro de cocina y zapatos de tacón. Elementos a corregir: Pelo suelto → pulsar el pelo para recogerlo. Mal olor en las axilas → pulsar las axilas para corregir la higiene personal. Zapatos de tacón → pulsar los zapatos para sustituirlos por calzado apropiado. Uñas pintadas de rojo → pulsar las manos para retirar el esmalte. | F11: Feedback por acierto: Personaje 1: - Barba larga: ¡Bien! La barba puede acumular microorganismos y restos de comida. Debe cubrirse con una redecilla de protección. - Uñas sucias: ¡Correcto! Las uñas sucias son un foco de contaminación. Hay que mantenerlas cortas y limpias. - Móvil en el bolsillo: ¡Muy bien! El móvil acumula microorganismos y no debe llevarse durante la manipulación de alimentos. - Pendiente largo: ¡Bien visto! Los pendientes grandes pueden caerse y contaminar los alimentos. No deben llevarse durante la jornada. Personaje 2: - Camiseta de tirantes: ¡Correcto! La ropa de calle no sirve como uniforme. Debe usarse la camisa del uniforme, limpia. - Reloj: ¡Bien! El reloj puede acumular suciedad y microorganismos. Debe retirarse antes de manipular alimentos. - Mancha en el pantalón: ¡Muy bien! El uniforme debe estar limpio. Si se mancha, hay que cambiarlo o limpiarlo. - Sin gorro: ¡Correcto! El gorro de cocina es obligatorio para evitar que el pelo caiga en los alimentos. Personaje 3: - Pendientes enormes: ¡Bien! Los pendientes grandes pueden desprenderse y contaminar los alimentos. Deben retirarse. - Brazalete: ¡Correcto! Las joyas acumulan suciedad y pueden caerse. No deben llevarse durante la manipulación. - Uñas largas: ¡Muy bien! Las uñas deben estar cortas y limpias para evitar acumular suciedad y contaminar los alimentos. - Sin gorro: ¡Correcto! El gorro de cocina es obligatorio para evitar que el pelo caiga en los alimentos. Personaje 4: - Pelo suelto: ¡Bien! El pelo debe llevarse recogido y cubierto por el gorro para evitar que caiga en los alimentos. - Mal olor en las axilas: ¡Correcto! La higiene corporal es imprescindible. Una ropa limpia no sustituye una higiene personal adecuada. - Zapatos de tacón: ¡Muy bien! El calzado debe ser apropiado para trabajar: cerrado, cómodo, antideslizante y seguro. - Uñas pintadas: ¡Bien visto! El esmalte puede desprenderse y caer en los alimentos. Las uñas deben llevarse sin pintar, cortas y limpias. Feedback por error: Si pulsa un elemento que no debe corregirse: Ese elemento no supone un problema para la seguridad alimentaria. | G11: ='Cont-Obj'!E:E -> 2.3 Cabello, barba, uñas y joyas
A12: ='Cont-Obj'!A:A -> Módulo 2. Higiene personal del manipulador | B12: ='Cont-Obj'!B:B -> O2.4 Ejecutar correctamente el lavado y secado de manos. | C12: ='Cont-Obj'!C:C -> 9 | D12: Cocina (vista fregadero) | E12: Título de la actividad: Manos a la obra: el lavado perfecto. Enunciado: Tus manos son la herramienta más importante… y también la vía más fácil para contaminar un alimento. A la derecha encontrarás la checklist con los pasos para un lavado correcto. Tu misión es completarlos todos en orden. Si te saltas un paso o no completas bien el movimiento, no avanzarás. Solo cuando termines la lista tendrás unas manos listas para manipular alimentos con seguridad. ¿Te atreves? Descripción: Actividad interactiva tipo simulación motora. En pantalla se ven unas manos en primer plano con un fregadero al fondo. El alumnado debe completar el procedimiento de lavado de manos siguiendo una checklist en el lado derecho de la pantalla. Cada paso exige un gesto concreto con el ratón o el dedo sobre las manos. Cuando el gesto se completa correctamente, el ítem se tacha automáticamente. Los pasos deben realizarse en orden: si se intenta ejecutar un paso que no toca, no avanza. Y si toca una superficie en el proceso, empezará de nuevo con el lavado. Se trabaja de forma práctica el procedimiento oficial de lavado de manos. Pasos y gestos que debe realizar el alumnado: - Paso 1. Mojar las manos con agua potable. Gesto: arrastrar el ratón desde las manos hacia el grifo para activarlo y mantener pulsado hasta que el agua cubra las manos. - Paso 2. Aplicar jabón líquido suficiente. Gesto: pulsar el dosificador de jabón (clic) y arrastrar el jabón hasta las manos. - Paso 3. Frotar durante al menos 20 segundos. Gesto: frotar las palmas entre sí con movimientos circulares y rápidos. Aparece un contador de 20 segundos en pantalla que solo avanza mientras se frota. - Paso 4. Limpiar bien las palmas, el dorso, los espacios entre los dedos, las yemas, los pulgares, las uñas y las muñecas. Gesto: secuencia guiada por símbolos en pantalla: Palmas: círculos amplios con ambas manos enfrentadas. Dorso: movimiento de arriba abajo con los dedos entrelazados. Espacios entre los dedos: zigzag entre los dedos. Yemas: pequeños círculos con las puntas de los dedos sobre la palma contraria. Pulgares: giros circulares alrededor del pulgar. Uñas: frotar las uñas contra la palma contraria. Muñecas: círculos alrededor de la muñeca. A medida que el alumnado completa cada zona, aparecen marcas de verificación parciales dentro del propio paso. - Paso 5. Aclarar completamente con agua corriente. Gesto: arrastrar de nuevo hacia el grifo y mantener hasta que desaparezca toda la espuma. - Paso 6. Secar bien las manos utilizando el sistema higiénico establecido, preferiblemente papel desechable. Gesto: coger una toalla de papel (clic) y frotarla sobre las manos con movimiento de arriba abajo hasta que queden secas. | F12: Feedback por acierto: Paso 1 – ¡Bien hecho! Paso 2 – ¡Muy bien! Paso 3 – ¡Perfecto! Paso 4 – ¡Estupendo! Paso 5 – ¡Fabuloso! Paso 6 – ¡Excelente! Paso 7 – ¡Crack! Feedback de error: Si intenta ejecutar un paso que no toca: "Aún no es el turno de ese paso. Sigue la checklist en orden: cada paso prepara el siguiente." Si en algún momento toca alguna superficie: "Has tocado una superficie contaminada. Después del lavado, evita pomos, grifos y alimentos crudos: volverías a contaminar las manos." Empieza de nuevo el lavado de manos. | G12: ='Cont-Obj'!E:E -> 2.4 El lavado de manos
A13: ='Cont-Obj'!A:A -> Módulo 2. Higiene personal del manipulador | B13: ='Cont-Obj'!B:B -> O2.5 Identificar en qué situaciones deben ser lavadas las manos | C13: ='Cont-Obj'!C:C -> 10 | D13: Cocina | E13: Título de la actividad: ¿Te lavarías las manos? Enunciado: Durante tu jornada, tus manos tocan decenas de cosas, y no todas ellas son igual de seguras. En pantalla irán apareciendo situaciones reales de trabajo. En cada una, decide si es necesario lavarse las manos antes de continuar. Cada situación es independiente: no te dejes llevar por lo que hayas respondido antes. ¡Demuestra que sabes cuándo toca lavarse las manos! Descripción: Actividad interactiva de decisión binaria. Se presentan, una a una, tarjetas pictograma con situaciones cotidianas de la jornada de un manipulador de alimentos. Cada tarjeta incluye una ilustración y una breve definición. Bajo la tarjeta aparecen dos cajones: Sí y No. El alumnado debe decidir si en esa situación es necesario lavarse las manos antes de continuar con otra tarea. Las situaciones se alternan para que el alumnado valore cada caso de forma independiente, sin dejarse llevar por la inercia. Situaciones a valorar: 1. Acabas de cobrar con dinero en efectivo --> Si 2. Tus manos están limpias y vas a cortar verduras en una tabla límpia --> No 3. Acabas de tocarte el pelo --> Si 4. Acabas de etiquetar un envase con la fecha --> No 5. Acabas de usar el teléfono móvil --> Si 6. Vas a servir un plato ya terminado --> No 7. Acabas de sonarte la nariz --> Si 8. Acabas de colocar los cubiertos limpios y secos y ahora tocan los platos --> No 9. Acabas de fregar el suelo con la fregona --> Sí 10. Acabas de recoger algo del suelo --> Si 11. Tus manos están limpias y vas a doblar unas servilletas --> No 12. Acabas de limpiar la encimera con un producto químico --> Si 13. Vas a emplatar unas verduras ya lavadas --> No 14. Has terminado de preparar el pollo y tienes que cortar verdura --> Si | F13: 1. ¡Correcto! / Incorrecto: El dinero pasa por muchas manos y es una fuente de contaminación. Después de tocarlo, hay que lavarse las manos antes de manipular alimentos. 2. ¡Correcto! / Incorrecto: No ha habido contacto con ninguna fuente de contaminación y la tabla está limpia. No es necesario un nuevo lavado por ese motivo. 3. ¡Correcto! / Incorrecto: El pelo puede acumular grasa, polvo y microorganismos. Después de tocarlo, hay que lavarse las manos antes de seguir manipulando alimentos. 4. ¡Correcto! / Incorrecto: Etiquetar un envase no implica contacto con fuentes de contaminación. No es necesario lavarse las manos por ese motivo. 5. ¡Correcto! / Incorrecto: El móvil es uno de los objetos que más microorganismos acumula y rara vez se limpia. Tras usarlo, hay que lavarse las manos. 6. ¡Correcto! / Incorrecto: Si las manos están limpias y no han tocado nada contaminante, no es necesario un nuevo lavado para servir un plato terminado. 7. ¡Correcto! / Incorrecto: Sonarse la nariz contamina las manos con secreciones y microorganismos. Es obligatorio lavarse las manos inmediatamente después. 8. ¡Correcto! / Incorrecto: Los platos ya están limpios y secos, y la tarea no implica contacto con fuentes de contaminación. No hace falta un nuevo lavado. 9. ¡Correcto! / Incorrecto: La fregona, el agua sucia y el suelo son fuentes claras de contaminación. Después de fregar, hay que lavarse las manos antes de tocar alimentos. 10. ¡Correcto! / Incorrecto: El suelo es una de las superficies más contaminadas. Después de recoger algo del suelo, hay que lavarse las manos. 11. ¡Correcto! / Incorrecto: Doblar servilletas limpias no implica contacto con fuentes de contaminación. No es necesario lavarse las manos por ese motivo. 12. ¡Correcto! / Incorrecto: Los productos químicos de limpieza pueden dejar residuos en las manos y contaminar los alimentos. Hay que lavarse las manos después de usarlos. 13. ¡Correcto! / Incorrecto: Si las manos están limpias y las verduras ya han sido lavadas, no es necesario un nuevo lavado para emplatarlas. 14. ¡Correcto! / Incorrecto: El pollo crudo es una fuente importante de contaminación. Al cambiar de tarea, hay que lavarse las manos para evitar contaminar la verdura. | G13: ='Cont-Obj'!E:E -> 2.4 El lavado de manos
A14: ='Cont-Obj'!A:A -> Módulo 2. Higiene personal del manipulador | B14: ='Cont-Obj'!B:B -> O2.6 Determinar cuándo es necesario cambiar los guantes y cómo utilizarlos de forma segura. | C14: ='Cont-Obj'!C:C -> 11 | E14: Actividad de lectura: Enunciado: | G14: ='Cont-Obj'!E:E -> 2.5 El uso correcto de los guantes
A15: ='Cont-Obj'!A:A -> Módulo 2. Higiene personal del manipulador | B15: ='Cont-Obj'!B:B -> O2.7 Aplicar el procedimiento establecido ante heridas y lesiones durante la manipulación de alimentos. | C15: ='Cont-Obj'!C:C -> 12 | D15: Cocina (pared botiquín) | E15: Título de la actividad: Heridas a raya: protege, decide y trabaja seguro. Enunciado: Parte 1 – Simulación: Te has hecho una pequeña herida en la mano y estás en plena jornada en la cocina. Antes de volver a manipular alimentos, debes protegerla correctamente. Alrededor de tus manos tienes varias herramientas. Selecciona y ejecuta los pasos necesarios para dejar la herida limpia y bien cubierta. Parte 2 – Test: Ahora demuestra que sabes decidir. En cada situación, elige la opción correcta. Descripción: Actividad mixta de simulación + test. En la primera parte, el alumnado ve unas manos en primer plano con una pequeña herida y debe ejecutar correctamente los pasos para protegerla antes de volver a manipular alimentos. En la segunda parte, se plantean distintas situaciones relacionadas con lesiones en forma de test de 3 opciones (solo una correcta). Se trabajan las normas de actuación ante heridas, cortes y otras lesiones de la piel en el entorno alimentario. Pasos de la simulación (estos pasos no aparecen escritos, el alumnado actua por descubrimiento): Paso 1. Limpiar y desinfectar correctamente la herida. Gesto: pulsar el algodón (se moverá al centro de la pantalla)→ arrastrar el bote de desinfectante de heridas al algodón (se humedecerá y desaparecerá el bote)→ frotar suavemente sobre la herida (tras esto, desaparecerá el algodón) Paso 2. Protegerla con un apósito impermeable y bien ajustado. Gesto: pulsar el apósito (se moverá al centro de la pantalla)→ pulsar las tijeras y llévalas al apósito (se cortará el apósito y desaparecerá la tijera) → pulsar sobre la herida para colocarlo → arrastrar el ratón sobre el apósito para pegarlo bien. Paso 3. Colocarse un guante de un solo uso cuando exista riesgo de que el apósito pueda desprenderse. Gesto: pulsar el guante → arrastrarlo hasta la mano para colocarlo. Situaciones tipo test: 1. Herida limpia y correctamente cubierta con un apósito impermeable. ✅ Puede continuar trabajando. ❌ Debe informar al responsable y dejar de manipular alimentos. ❌ Debe retirarse el apósito antes de continuar. 2. Herida en la mano cubierta, pero el apósito puede desprenderse durante el trabajo. ✅ Debe protegerse además con un guante de un solo uso. ❌ Puede continuar sin cambios, porque la herida ya está cubierta. ❌ Debe informar al responsable y abandonar la manipulación de alimentos. 3. Herida con presencia de pus. ✅ Debe informar al responsable. ❌ Puede continuar si se limpia con alcohol antes de trabajar. ❌ Puede continuar si se cubre con doble apósito. 4. Herida que no puede cubrirse completamente con un apósito ni con un guante. ✅ Debe informar al responsable. ❌ Puede continuar si se coloca un guante por encima. ❌ Puede continuar si evita tocar los alimentos directamente. 5. Lesión que te impide mover la mano con normalidad y trabajar de forma segura. ✅ Debe informar al responsable para valorar un cambio de tarea o dejar de manipular alimentos. ❌ Puede continuar si se coloca un guante de un solo uso. ❌ Puede continuar si se cubre la lesión con un apósito impermeable. | F15: Parte 1 – Simulación: Por cada paso correcto, refuerzo positivo: ¡Bien hecho! ¡Muy bien! ¡Perfecto! ¡Estupendo! ¡Excelente! Si no pulsa donde toca simplemente no pasa nada, no avanza. Parte 2 – Test: 1. Herida limpia y bien cubierta con apósito impermeable. ¡Correcto! / Incorrecto: Si la herida está limpia y correctamente cubierta con un apósito impermeable, se puede continuar trabajando con normalidad. 2. Herida cubierta, pero el apósito puede desprenderse. ¡Correcto! / Incorrecto: Si existe riesgo de que el apósito se desprenda durante el trabajo, hay que proteger la herida además con un guante de un solo uso. 3. Herida abierta y sin proteger. ¡Correcto! / Incorrecto: Nunca se deben manipular alimentos con una herida abierta y sin proteger. Es una fuente directa de contaminación. 4. Herida infectada. ¡Correcto! / Incorrecto: Una herida infectada puede contener microorganismos peligrosos. Es obligatorio informar al responsable antes de continuar. 5. Herida con presencia de pus. ¡Correcto! / Incorrecto: La presencia de pus indica infección. No se debe manipular alimentos y hay que informar al responsable de inmediato. 6. Herida que no puede cubrirse adecuadamente. ¡Correcto! / Incorrecto: Si la herida no puede cubrirse bien, no hay garantía de que no contamine los alimentos. Hay que informar al responsable. 7. Lesión que impide trabajar de forma segura. ¡Correcto! / Incorrecto: Si la lesión impide trabajar con seguridad, hay que informar al responsable para que valore un cambio de tarea o dejar de manipular alimentos. | G15: ='Cont-Obj'!E:E -> 2.6 Heridas y cortes
A16: ='Cont-Obj'!A:A -> Módulo 3. Manipulación segura de los alimentos | B16: ='Cont-Obj'!B:B -> O3.1 Identificar qué es la contaminación alimentaria y reconocer cómo puede producirse a lo largo de las distintas etapas de la cadena alimentaria. | C16: ='Cont-Obj'!C:C -> 13 | E16: Actividad de lectura: Enunciado: | G16: ='Cont-Obj'!E:E -> 3.1 ¿Qué es la contaminación alimentaria?
A17: ='Cont-Obj'!A:A -> Módulo 3. Manipulación segura de los alimentos | B17: ='Cont-Obj'!B:B -> O3.2 Distinguir los diferentes tipos de contaminación alimentaria: biológica, física y química. | C17: ='Cont-Obj'!C:C -> 14 | E17: Actividad de lectura: Enunciado: | G17: ='Cont-Obj'!E:E -> 3.2 ¿Cómo pueden contaminarse los alimentos?
A18: ='Cont-Obj'!A:A -> Módulo 3. Manipulación segura de los alimentos | B18: ='Cont-Obj'!B:B -> O3.3 Identificar las principales fuentes y vías de contaminación de los alimentos durante su manipulación. | C18: ='Cont-Obj'!C:C -> 15 | E18: Título de la actividad: Tras la barra. Enunciado: Estás detrás de la barra y varios clientes se acercan con quejas sobre sus platos. Algo ha ido mal en la cocina y tu misión es descubrir qué tipo de contaminación ha afectado a cada alimento: física, química o biológica. Haz clic en cada plato para investigarlo. En algunos casos verás la evidencia directamente; en otros, tendrás que revisar las cámaras de seguridad pulsando el icono de la cámara. Observa bien, reúne las pistas y selecciona el tipo de contaminación. ¡Demuestra que no se te escapa nada!" Descripción: Actividad interactiva de investigación. El alumnado se sitúa detrás de la barra de un establecimiento y varios clientes se acercan con quejas sobre distintos platos. Al hacer clic en cada plato, se muestra en primer plano (vista desde arriba). Según el caso, habrá una evidencia visible (pelo, plástico, moho…) o no, en cuyo caso aparecerá un icono de cámara para revisar las grabaciones de seguridad de la cocina en el momento de la preparación. Una vez reunida la pista, el alumnado debe identificar el tipo de contaminación: física, química o biológica. Se trabajan los tres tipos de contaminación y la importancia de no fiarse solo de los sentidos. CASO 1 Cliente: "He encontrado un pelo en la comida. No es mío, yo llevo el pelo recogido." Qué ve el alumnado al revisar el plato: Hay un cabello largo y oscuro, claramente visible, que no forma parte del plato. Respuesta: Contaminación física. CASO 2 Cliente: "No he notado nada raro en el plato, pero después de comerlo me he encontrado mal." Qué ve el alumnado al revisar el plato: No se aprecia ningún objeto extraño ni alteración visible. El alimento parece normal a la vista. Aparece el icono de cámara en la esquina superior derecha. Qué ve el alumnado en las cámaras: Se observa cómo, durante la preparación, el manipulador utiliza un utensilio que acababa de estar en contacto con carne cruda y no lo ha lavado antes de utilizarlo con este alimento. El utensilio pasa directamente de un alimento crudo a este plato. Respuesta: Contaminación biológica. CASO 3 Cliente: "Al masticar he notado algo duro. Creo que hay un trozo de algo que no es comida." Qué ve el alumnado al revisar el plato: Entre los alimentos hay un pequeño fragmento de plástico (un trozo de un envase), claramente visible. Respuesta: Contaminación física. CASO 4 Cliente: "El plato tiene un sabor raro, como a producto de limpieza. Sabe mal." Qué ve el alumnado al revisar el plato: El plato se ve completamente normal: buen aspecto, buen color, sin objetos extraños. Aparece el icono de cámara. Qué ve el alumnado en las cámaras: En la grabación se observa cómo, durante la limpieza de la zona de trabajo, se utilizó un producto químico y quedaron restos del producto sobre una superficie que posteriormente entró en contacto con este alimento. El manipulador no aclaró ni secó bien la superficie antes de apoyar el alimento. Respuesta: Contaminación química. CASO 5 Cliente: "El plato olía raro y, después de comerlo, he empezado a encontrarme mal." Qué ve el alumnado al revisar el plato: El plato se ve completamente normal: buen aspecto, buen olor, sin alteraciones visibles. Aparece el icono de cámara. Qué ve el alumnado en las cámaras: Se observa cómo, durante la preparación, el manipulador manipula el alimento con las manos sin lavárselas después de haber tocado basura. Los microorganismos pasan al alimento sin dejar rastro visible. Respuesta: Contaminación biológica. CASO 6 Cliente: "Creo que hay algo en el plato que no es comida. Parece un trozo de algo… de un pendiente, quizá." Qué ve el alumnado al revisar el plato: Entre los alimentos, hay un pequeño elemento procedente de un objeto personal del manipulador (la tuerca de un pendiente), claramente visible. Respuesta: Contaminación física. CASO 7 Cliente: «La salsa tiene un sabor extraño. No sé qué le habéis puesto, pero no sabe como siempre». Qué ve el alumnado al revisar el plato: El plato parece normal a simple vista, sin objetos extraños ni alteraciones visibles. Aparece el icono de cámara. Qué ve el alumnado en las cámaras: En la grabación se observa cómo un manipulador utiliza un bote de salsa que se había almacenado junto a un producto químico para el control de plagas. El exterior del bote se ha contaminado con restos del producto y, al abrirlo y manipularlo, estos entran en contacto con la salsa. Respuesta: Contaminación química. | F18: Caso 1 – Cabello en el plato: ¡Correcto! / Incorrecto: Un cabello es un objeto extraño que no debería estar en el alimento. Es una contaminación física. Caso 2 – Olor extraño por utensilio sucio: ¡Correcto! / Incorrecto: Los microorganismos del alimento crudo han pasado al plato a través de un utensilio sucio. Es una contaminación biológica, y no se ve a simple vista. Caso 3 – Fragmento de plástico: ¡Correcto! / Incorrecto: Un fragmento de plástico es un objeto ajeno al alimento. Es una contaminación física. Caso 4 – Sabor a producto de limpieza: ¡Correcto! / Incorrecto: Los restos de productos químicos de limpieza han entrado en contacto con el alimento. Es una contaminación química. Caso 5 – Alimento aparentemente normal que causa enfermedad: ¡Correcto! / Incorrecto: Los microorganismos pueden estar en el alimento sin que se vean, huelan o sepan. Es una contaminación biológica. Caso 6 – Objeto personal en el plato: ¡Correcto! / Incorrecto: Los objetos personales pueden desprenderse y caer en la comida. Es una contaminación física. Caso 7 – Restos de producto de limpieza: ¡Correcto! / Incorrecto: Los restos de productos de limpieza pueden contaminar el alimento si no se aclaran bien las superficies. Es una contaminación química. Feedback de error general (si el alumnado elige mal el tipo de contaminación): Si confunde física: "Recuerda: la contaminación física aparece cuando en el alimento se encuentra un objeto o elemento que no debería estar presente." Si confunde química: "Recuerda: la contaminación química se produce cuando el alimento entra en contacto con una sustancia química perjudicial." Si confunde biológica: "Recuerda: la contaminación biológica se produce cuando el alimento contiene microorganismos o parásitos capaces de causar enfermedades." | G18: ='Cont-Obj'!E:E -> 3.2 ¿Cómo pueden contaminarse los alimentos?
A19: ='Cont-Obj'!A:A -> Módulo 3. Manipulación segura de los alimentos | B19: ='Cont-Obj'!B:B -> O3.4 Comprender cómo se produce la contaminación cruzada. | C19: ='Cont-Obj'!C:C -> 16 | E19: Actividad de lectura: Enunciado: Idea: Incluir información sobre la contaminación directa e indirecta. Los alimentos crudos pueden contener microorganismos que contaminen otros alimentos. La contaminación cruzada ocurre cuando esos microorganismos pasan de un alimento, una superficie, un utensilio o las manos a otro alimento. Puede producirse por contacto directo entre alimentos o de forma indirecta a través de manos, utensilios y superficies. Los alimentos listos para consumir deben mantenerse protegidos y separados de posibles fuentes de contaminación. Cuando cambies de tarea, debes evitar que la contaminación pase al siguiente alimento. | G19: ='Cont-Obj'!E:E -> 3.3 La contaminación cruzada
A20: ='Cont-Obj'!A:A -> Módulo 3. Manipulación segura de los alimentos | B20: ='Cont-Obj'!B:B -> O3.5 Reconocer situaciones que pueden provocar contaminación cruzada y diferenciar entre contaminación cruzada directa e indirecta. | C20: ='Cont-Obj'!C:C -> 17 | E20: Título de la actividad: De la tabla a la nevera: prepara y almacena sin contaminar. Enunciado: El restaurante está a punto de abrir y tienes que dejar los alimentos preparados y bien almacenados. En esta misión tienes dos tareas encadenadas: Parte 1 – Prepara: corta cada alimento y guardarlo en un recipiente adecuado. Organiza el trabajo como quieras, pero evita que se produzca contaminación cruzada durante la preparación. Parte 2 – Almacena: cuando tengas todos los recipientes cerrados, colócalos en la nevera. Tú decides la ubicación de cada uno, pero recuerda evitar la contaminacion cruzada durante el almacenamiento. No recibirás indicaciones: demuestra que tienes el control de la cocina y que sabes prevenir la contaminación cruzada en todo el proceso. ¡Adelante! Descripción: Actividad interactiva de simulación en dos partes encadenadas. El alumnado debe preparar y almacenar correctamente los alimentos antes de la apertura del restaurante, aplicando medidas para prevenir la contaminación cruzada en todo el proceso. Parte 1 – Preparación: el alumnado corta los alimentos y los guarda en recipientes cerrados, decidiendo por sí mismo cuándo lavarse las manos, cambiar de utensilio, limpiar una superficie o evitar el contacto entre alimentos. El pollo crudo es el principal foco de riesgo, por lo que exige extremar las precauciones (tabla y cuchillo exclusivos, lavado de manos posterior, etc.). Parte 2 – Almacenamiento: el alumnado coloca los mismos recipientes (ya cerrados con los alimentos preparados) en una nevera con varios estantes, aplicando los principios de separación, protección y prevención de derrames. El pollo crudo debe ir en la zona inferior. La actividad no da indicaciones sobre estas decisiones: el alumnado debe aplicarlas según lo aprendido sobre prevención de contaminación cruzada. Si realiza una acción de riesgo, recibe un feedback inmediato que explica el error e identifica si se trata de contaminación cruzada directa o indirecta. La actividad termina cuando todos los alimentos están preparados, guardados en sus recipientes y correctamente almacenados en la nevera. Dinámica detallada: Alimentos disponibles (todos en cuencos independientes): - Pollo crudo (principal foco de riesgo). - Lechuga (listo para consumir). - Tomate (listo para consumir). - Jamón cocido (listo para consumir). - Queso (listo para consumir). (Nota: la lechuga, el tomate, el jamón cocido y el queso se consideran alimentos listos para consumir. Cualquier contacto con el pollo crudo o sus líquidos supone un riesgo real para el consumidor). Elementos disponibles: Parte 1: zona de trabajo, 2 tablas de corte, 2 cuchillos, zona de lavado y zona con recipientes para guardar los alimentos. Parte 2: nevera con diferentes estantes y los mismos cinco recipientes cerrados que el alumnado ha preparado en la Parte 1. PARTE 1 – Preparación El alumnado dispone de todos los alimentos en la zona de trabajo y elige libremente qué preparar en cada momento. Para cada uno: 1. Selecciona un cuenco y arrastra el alimento hasta la tabla de corte. 2. Corta el alimento con el cuchillo. 3. Decide si es necesario lavarse las manos, cambiar de utensilio o limpiarlos antes de continuar con otro alimento. 4. Abre un recipiente pulsando sobre la zona de recipientes. 5. Arrastra el alimento cortado hasta el recipiente. 6. El recipiente se cierra automáticamente y queda listo para la Parte 2. 7. Continúa con el siguiente alimento hasta completar todos. Puntos clave de la Parte 1: - El pollo crudo exige tabla y cuchillo exclusivos, y lavado de manos posterior. - No se debe cortar ningún alimento listo para consumir con los utensilios usados para el pollo crudo. - No se deben poner en contacto alimentos crudos y listos para consumir. - Las superficies y utensilios deben limpiarse entre usos cuando exista riesgo. PARTE 2 – Almacenamiento en la nevera Cuando todos los alimentos están preparados y en sus recipientes cerrados, comienza la segunda parte. El alumnado: 1. Selecciona un recipiente y lo arrastra hasta una posición disponible dentro de la nevera. El recipiente queda situado en la posición seleccionada. 2. Si la colocación es adecuada, el alumnado continúa con otro recipiente. 3. Si la ubicación presenta un riesgo, aparece un feedback que explica el problema y permite corregir la posición. Puntos clave de la Parte 2: - El pollo crudo debe colocarse en una zona inferior, para que sus líquidos no caigan sobre otros alimentos. - Los alimentos listos para consumir deben mantenerse separados del pollo crudo. El orden de colocación es libre y puede haber varias distribuciones correctas. La actividad termina cuando todos los recipientes están colocados de forma segura en la nevera. | F20: Feedback de la Parte 1: Feedback por error: 1. Utilizar el mismo cuchillo con otro alimento: Contaminación cruzada indirecta: Has utilizado un cuchillo que ha estado en contacto con otro alimento y puede transferir microorganismos al siguiente. Cambia de utensilio o límpialo antes de utilizarlo con otro alimento. 2. Utilizar la misma tabla con otro alimento: Contaminación cruzada indirecta: La tabla puede haber quedado contaminada durante la preparación anterior y puede transferir microorganismos. Cambia de tabla o límpiala antes de continuar. 3. Continuar con otro alimento sin lavarse las manos: Contaminación cruzada indirecta: Tus manos pueden transportar microorganismos de un alimento a otro. Lávate las manos antes de continuar con la preparación. 4. Poner dos alimentos en contacto: Contaminación cruzada directa: Un alimento ha entrado directamente en contacto con otro y puede transmitirle microorganismos. Mantén los alimentos separados durante la preparación. 5. Utilizar el cuchillo del pollo crudo para otro alimento (aunque se haya lavado): Contaminación cruzada indirecta: El cuchillo ha estado en contacto con pollo crudo. Lavarlo con agua y jabón no garantiza que se hayan eliminado los microorganismos que podrían contaminar el siguiente alimento. Como no dispones de medios para desinfectarlo, utiliza otro cuchillo limpio que no haya estado en contacto con el pollo crudo. 6. Utilizar la tabla del pollo crudo para otro alimento (aunque se haya lavado): Contaminación cruzada indirecta: La tabla ha estado en contacto con pollo crudo. Lavarlo con agua y jabón no garantiza que se hayan eliminado los microorganismos que podrían contaminar el siguiente alimento. Como no dispones de medios para desinfectarla, utiliza otra tabla limpia que no haya estado en contacto con el pollo crudo. Feedback de acierto final (al completar la actividad): ¡Preparación correcta! Has evitado la contaminación cruzada durante la manipulación. Has controlado el contacto entre los alimentos y has utilizado correctamente las manos, los utensilios y las superficies. Todos los alimentos están preparados y almacenados en recipientes cerrados. Feedback de la Parte 2: 1. Pollo crudo colocado encima de alimentos listos para consumir: ⚠️ Riesgo de contaminación cruzada indirecta. Si los líquidos del pollo crudo cayeran sobre los alimentos situados debajo, podrían transmitirles microorganismos. Coloca el pollo en una zona inferior y evita que sus líquidos puedan alcanzar otros alimentos. 2. Recipientes colocados de forma que existe riesgo de contaminación: ⚠️ Riesgo de contaminación cruzada. La ubicación de estos recipientes puede favorecer la transferencia de contaminación entre alimentos. Reorganízalos para evitar posibles contactos o derrames. 4. Pollo crudo correctamente colocado: ✓ Colocación correcta. Has mantenido el pollo crudo separado de los alimentos listos para consumir y has evitado que sus posibles líquidos puedan contaminarlos. 5. Alimento listo para consumir correctamente colocado: ✓ Colocación correcta. El alimento está protegido y su ubicación evita posibles contactos o contaminación procedente de otros productos. 6. Todos los recipientes correctamente almacenados (feedback final): ✓ Nevera organizada correctamente. Has mantenido los alimentos protegidos y separados, evitando que el pollo crudo pueda contaminar otros productos. La nevera está organizada de forma segura. | G20: ='Cont-Obj'!E:E -> 3.3 La contaminación cruzada
A21: ='Cont-Obj'!A:A -> Módulo 3. Manipulación segura de los alimentos | B21: ='Cont-Obj'!B:B -> O3.6 Aplicar medidas de prevención de la contaminación cruzada durante la preparación y almacenamiento. | C21: ='Cont-Obj'!C:C -> 17 | E21: Título de la actividad: De la tabla a la nevera: prepara y almacena sin contaminar. Enunciado: El restaurante está a punto de abrir y tienes que dejar los alimentos preparados y bien almacenados. En esta misión tienes dos tareas encadenadas: Parte 1 – Prepara: corta cada alimento y guardarlo en un recipiente adecuado. Organiza el trabajo como quieras, pero evita que se produzca contaminación cruzada durante la preparación. Parte 2 – Almacena: cuando tengas todos los recipientes cerrados, colócalos en la nevera. Tú decides la ubicación de cada uno, pero recuerda evitar la contaminacion cruzada durante el almacenamiento. No recibirás indicaciones: demuestra que tienes el control de la cocina y que sabes prevenir la contaminación cruzada en todo el proceso. ¡Adelante! Descripción: Actividad interactiva de simulación en dos partes encadenadas. El alumnado debe preparar y almacenar correctamente los alimentos antes de la apertura del restaurante, aplicando medidas para prevenir la contaminación cruzada en todo el proceso. Parte 1 – Preparación: el alumnado corta los alimentos y los guarda en recipientes cerrados, decidiendo por sí mismo cuándo lavarse las manos, cambiar de utensilio, limpiar una superficie o evitar el contacto entre alimentos. El pollo crudo es el principal foco de riesgo, por lo que exige extremar las precauciones (tabla y cuchillo exclusivos, lavado de manos posterior, etc.). Parte 2 – Almacenamiento: el alumnado coloca los mismos recipientes (ya cerrados con los alimentos preparados) en una nevera con varios estantes, aplicando los principios de separación, protección y prevención de derrames. El pollo crudo debe ir en la zona inferior. La actividad no da indicaciones sobre estas decisiones: el alumnado debe aplicarlas según lo aprendido sobre prevención de contaminación cruzada. Si realiza una acción de riesgo, recibe un feedback inmediato que explica el error e identifica si se trata de contaminación cruzada directa o indirecta. La actividad termina cuando todos los alimentos están preparados, guardados en sus recipientes y correctamente almacenados en la nevera. Dinámica detallada: Alimentos disponibles (todos en cuencos independientes): - Pollo crudo (principal foco de riesgo). - Lechuga (listo para consumir). - Tomate (listo para consumir). - Jamón cocido (listo para consumir). - Queso (listo para consumir). (Nota: la lechuga, el tomate, el jamón cocido y el queso se consideran alimentos listos para consumir. Cualquier contacto con el pollo crudo o sus líquidos supone un riesgo real para el consumidor). Elementos disponibles: Parte 1: zona de trabajo, 2 tablas de corte, 2 cuchillos, zona de lavado y zona con recipientes para guardar los alimentos. Parte 2: nevera con diferentes estantes y los mismos cinco recipientes cerrados que el alumnado ha preparado en la Parte 1. PARTE 1 – Preparación El alumnado dispone de todos los alimentos en la zona de trabajo y elige libremente qué preparar en cada momento. Para cada uno: 1. Selecciona un cuenco y arrastra el alimento hasta la tabla de corte. 2. Corta el alimento con el cuchillo. 3. Decide si es necesario lavarse las manos, cambiar de utensilio o limpiarlos antes de continuar con otro alimento. 4. Abre un recipiente pulsando sobre la zona de recipientes. 5. Arrastra el alimento cortado hasta el recipiente. 6. El recipiente se cierra automáticamente y queda listo para la Parte 2. 7. Continúa con el siguiente alimento hasta completar todos. Puntos clave de la Parte 1: - El pollo crudo exige tabla y cuchillo exclusivos, y lavado de manos posterior. - No se debe cortar ningún alimento listo para consumir con los utensilios usados para el pollo crudo. - No se deben poner en contacto alimentos crudos y listos para consumir. - Las superficies y utensilios deben limpiarse entre usos cuando exista riesgo. PARTE 2 – Almacenamiento en la nevera Cuando todos los alimentos están preparados y en sus recipientes cerrados, comienza la segunda parte. El alumnado: 1. Selecciona un recipiente y lo arrastra hasta una posición disponible dentro de la nevera. El recipiente queda situado en la posición seleccionada. 2. Si la colocación es adecuada, el alumnado continúa con otro recipiente. 3. Si la ubicación presenta un riesgo, aparece un feedback que explica el problema y permite corregir la posición. Puntos clave de la Parte 2: - El pollo crudo debe colocarse en una zona inferior, para que sus líquidos no caigan sobre otros alimentos. - Los alimentos listos para consumir deben mantenerse separados del pollo crudo. El orden de colocación es libre y puede haber varias distribuciones correctas. La actividad termina cuando todos los recipientes están colocados de forma segura en la nevera. | F21: Feedback de la Parte 1: Feedback por error: 1. Utilizar el mismo cuchillo con otro alimento: Contaminación cruzada indirecta: Has utilizado un cuchillo que ha estado en contacto con otro alimento y puede transferir microorganismos al siguiente. Cambia de utensilio o límpialo antes de utilizarlo con otro alimento. 2. Utilizar la misma tabla con otro alimento: Contaminación cruzada indirecta: La tabla puede haber quedado contaminada durante la preparación anterior y puede transferir microorganismos. Cambia de tabla o límpiala antes de continuar. 3. Continuar con otro alimento sin lavarse las manos: Contaminación cruzada indirecta: Tus manos pueden transportar microorganismos de un alimento a otro. Lávate las manos antes de continuar con la preparación. 4. Poner dos alimentos en contacto: Contaminación cruzada directa: Un alimento ha entrado directamente en contacto con otro y puede transmitirle microorganismos. Mantén los alimentos separados durante la preparación. 5. Utilizar el cuchillo del pollo crudo para otro alimento (aunque se haya lavado): Contaminación cruzada indirecta: El cuchillo ha estado en contacto con pollo crudo. Lavarlo con agua y jabón no garantiza que se hayan eliminado los microorganismos que podrían contaminar el siguiente alimento. Como no dispones de medios para desinfectarlo, utiliza otro cuchillo limpio que no haya estado en contacto con el pollo crudo. 6. Utilizar la tabla del pollo crudo para otro alimento (aunque se haya lavado): Contaminación cruzada indirecta: La tabla ha estado en contacto con pollo crudo. Lavarlo con agua y jabón no garantiza que se hayan eliminado los microorganismos que podrían contaminar el siguiente alimento. Como no dispones de medios para desinfectarla, utiliza otra tabla limpia que no haya estado en contacto con el pollo crudo. Feedback de acierto final (al completar la actividad): ¡Preparación correcta! Has evitado la contaminación cruzada durante la manipulación. Has controlado el contacto entre los alimentos y has utilizado correctamente las manos, los utensilios y las superficies. Todos los alimentos están preparados y almacenados en recipientes cerrados. Feedback de la Parte 2: 1. Pollo crudo colocado encima de alimentos listos para consumir: ⚠️ Riesgo de contaminación cruzada indirecta. Si los líquidos del pollo crudo cayeran sobre los alimentos situados debajo, podrían transmitirles microorganismos. Coloca el pollo en una zona inferior y evita que sus líquidos puedan alcanzar otros alimentos. 2. Recipientes colocados de forma que existe riesgo de contaminación: ⚠️ Riesgo de contaminación cruzada. La ubicación de estos recipientes puede favorecer la transferencia de contaminación entre alimentos. Reorganízalos para evitar posibles contactos o derrames. 4. Pollo crudo correctamente colocado: ✓ Colocación correcta. Has mantenido el pollo crudo separado de los alimentos listos para consumir y has evitado que sus posibles líquidos puedan contaminarlos. 5. Alimento listo para consumir correctamente colocado: ✓ Colocación correcta. El alimento está protegido y su ubicación evita posibles contactos o contaminación procedente de otros productos. 6. Todos los recipientes correctamente almacenados (feedback final): ✓ Nevera organizada correctamente. Has mantenido los alimentos protegidos y separados, evitando que el pollo crudo pueda contaminar otros productos. La nevera está organizada de forma segura. | G21: ='Cont-Obj'!E:E -> 3.3 La contaminación cruzada
A22: ='Cont-Obj'!A:A -> Módulo 3. Manipulación segura de los alimentos | B22: ='Cont-Obj'!B:B -> O3.7 Evaluar si las materias primas cumplen las condiciones de seguridad para su recepción. | C22: ='Cont-Obj'!C:C -> 18 | E22: Título de la actividad: Recepción a examen: acepta o rechaza. Enunciado: Acaba de llegar un pedido al restaurante y tu misión es inspeccionarlo antes de guardarlo. No todo lo que llega en el camión es apto para el consumo. Explora el vehículo y las cajas, revisa cada detalle (limpieza, envases, etiquetas, fechas, temperaturas, aspecto de los alimentos y documentación) y decide qué se acepta y qué no. Cuando encuentres un producto que no cumpla las condiciones, recházalo y comunica la incidencia al responsable.¡Haz una recepción de diez!" Descripción: Actividad interactiva de inspección. El alumnado se sitúa en la zona de recepción de mercancías de un restaurante. En pantalla se ve la parte trasera del restaurante y parte de carga del camión de reparto, con la puerta abierta y varias cajas de alimentos en su interior. El alumnado debe explorar e inspeccionar el vehículo, las cajas, las etiquetas, las temperaturas y el aspecto de los alimentos antes de decidir qué mercancía puede aceptarse. Cuando detecte una anomalía, deberá rechazar el producto. Dinámica de juego: el alumno dispondrá de una checklist con items que cumplir. Esta check list estará en miniatura en la parte superior derecha de la pantalla para comprobarla siempre que lo necesite. Conforme se vayan completando los items, estos apareceran tachados en la checklist. Además, los objetos o lugares donde deba pulsar tendrán un hover highlight. Al ser pulsados son enfocados en primer plano y debajo aparecerán las dos opciones: aceptar o rechazar y comunicar incidencia. Una vez completado un item de la checklist, el hover highlight desaparecerá y ya no podrá acceder de nuevo a ese punto interactivo. Elementos de la check list: ☐ Comprobar proveedor autorizado ☐ Revisar vehículo de transporte ☐ Inspeccionar envases y embalajes ☐ Revisar etiquetado e identificación ☐ Medir temperatura de refrigerados. Rango correcto ≤ 4 °C ☐ Medir temperatura de congelados. Rango correcto ≤ -18 °C ☐ Revisar signos de descongelación/recongelación ☐ Inspeccionar estado de los alimentos ☐ Comprobar ausencia de deterioro, moho o plagas ☐ Revisar documentación de la entrega 1. Proveedor autorizado Hover highlight: el lateral del camión con el nombre de la empresa de reparto. Al pulsarlo se abre una ficha del proveedor con: nombre de la empresa, nº de registro sanitario, sello de "Proveedor autorizado" y listado de productos que suministra. Conclusión: ACEPTAR (proveedor registrado y autorizado). 2. Vehículo de transporte Hover highlight: puerta del camión. Scene transition al interior del camión que se ve ordenado y reluciente. Conclusión: ACEPTAR (vehículo ordenado y limpio). 3. Envases y embalajes Hover highlight: cajas apiladas en el interior del camión. Scene transition al conjunto de cajas apiladas. Hover highlight: tres cajas, cada una se pulsa individualmente. Al pulsarlas: - Caja de leche: al pulsarla, se acerca la imagen y se ve un golpe en una esquina con una fuga de líquido. El envase está húmedo y abollado. - Caja de galletas: al pulsarla, se ve que el cartón está roto y aplastado. - Caja de magdalenas: al pulsarla, se ve que el cartón está limpio, cerrado y en buen estado. Conclusión: - Caja de leche: RECHAZAR Y COMUNICAR (embalaje en mal estado, fuga de líquido). - Caja de galletas: RECHAZAR Y COMUNICAR (embalaje roto y mercancía aplastada). - Caja de magdalenas: ACEPTAR (embalaje en buen estado). 4. Etiquetado e identificación Hover highlight: nevera vertical con vitrina. Dentro lleva conservas, lacteos y salsas envasadas. Scene transition al interior de la nevera (nevera abierta en primer plano). Hover highlight: balda de las latas de conserva, balda de los yogures y balda de las salsas. Se pulsan y salen los productos individualmente (una lata, un yogurt y un bote de salsa). Al pulsarlas: - Caja de yogures: aparece la etiqueta correcta: nombre del producto, marca, fecha de caducidad y lote. - Lata de conservas: aparece la etiqueta en blanco, sin nombre, sin ingredientes, sin origen y sin fecha. No hay identificación. - Bote de salsa: aparece la etiqueta correcta: nombre, ingredientes, fecha de caducidad y lote. Conclusión: - Lata de conservas: RECHAZAR Y COMUNICAR (mal etiquetado). - Yogures y salsa: ACEPTAR (etiquetado correcto). 5. Temperatura de productos refrigerados Hover highlight: nevera vertical gris. Scene transition al interior de la nevera con carne envasada (nevera abierta en primer plano). A la derecha aparece un termómetro. El alumno deberá arrastrarlo al interior de la nevera y esperar un par de segundos. La pantalla del termómetro se colocará en primer plano marcando 7 ºC. Conclusión: RECHAZAR Y COMUNICAR (temperatura inadecuada). 6. Temperatura de productos congelados Hover highlight: congelador vertical blanco. Scene transition al interior del congelador con pescado congelado (congelador abierto en primer plano). A la derecha aparece un termómetro. El alumno deberá arrastrarlo al interior del congelador y esperar un par de segundos. La pantalla del termómetro se colocará en primer plano marcando -18 ºC. Conclusión: ACEPTAR (temperatura adecuada). 7. Signos de descongelación o recongelación en congelados Partiendo de la escena anterior, sin salir del congelador, hover highlight: caja de pescado congelado. Al pulsarla sale un filete de atún parcialmente descongelado. El pescado presenta zonas blandas y húmedas, mientras otras siguen congeladas. Es una señal visual más directa de que el producto no está completamente congelado en el momento de la recepción. Conclusión: RECHAZAR Y COMUNICAR (signos claros de ruptura de la cadena de frío). 8. Ausencia de deterioro, suciedad, moho o plagas Hover highlight: Tres cestas de fruta en un lado del interior del camión. Scene transition a las tres cestas. Hover highlight cada una de las tres cestas. Al pulsarlas: - Cesta de manzanas: se ven las manzanas brillantes, sin moho ni plagas. - Cesta de limones: se ven los limones brillantes, sin moho ni plagas. - Cesta de tomates: se ven varios tomates con moho y un insecto entre la mercancía. Conclusión: - Cesta de manzanas: ACEPTAR (mercancía en bues estado). - Cesta de limones: ACEPTAR (mercancía en bues estado). - Cesta de tomates: RECHAZAR Y COMUNICAR (signos claros moho y plaga). 9. Documentación de la entrega Hover highlight: carpeta visible en la pared del camión, a la izquierda de la entrada. Al pulsarlo se abre el albarán de entrega con: nombre del proveedor, listado de productos y cantidades, fechas de entrega y caducidad, nº de lote y firma del repartidor. A la derecha aparece un icono en miniatura para poder abrir el pedido realizado. Al pulsarlo se abre a la derecha del albarán de entrega. El alumno deberá comparar el albarán de entrega con el pedido realizado: coincide. Conclusión: ACEPTAR (documentación correcta y coincidente con el pedido). | F22: Feedback por situación: 1. Proveedor autorizado: ¡Correcto! / Incorrecto: Es imprescindible comprobar que los productos proceden de un proveedor autorizado para garantizar su trazabilidad y seguridad. 2. Vehículo de transporte: ¡Correcto! / Incorrecto: El vehículo debe estar limpio, en buen estado y en condiciones adecuadas de transporte. 3. Envases y embalajes: ¡Correcto! / Incorrecto: Un envase golpeado, abollado o con fugas puede haber contaminado el producto. Debe separarse y comunicarse. 4. Etiquetado: ¡Correcto! / Incorrecto: Un producto sin etiqueta no tiene identificación ni trazabilidad, no puede aceptarse. 5. Temperatura de refrigerados: ¡Correcto! / Incorrecto: Una temperatura de 7 °C en refrigerados está por encima de lo establecido (≤ 4 °C). El producto no es seguro y debe separarse. 6. Temperatura de congelados: ¡Correcto! / Incorrecto: -18 °C es la temperatura correcta en congelados para que el producto puede aceptarse. 7. Descongelación/recongelación: ¡Correcto! / Incorrecto: La escarcha excesiva es un signo de descongelación y recongelación. El producto no es seguro. 8. Estado de los alimentos: ¡Correcto! / Incorrecto: El moho y la presencia de insectos indican deterioro y falta de higiene. El producto debe separarse y comunicarse. Si la fruta y la verdura presentan el aspecto, color y firmeza esperados, pueden aceptarse. 9. Documentación: ¡Correcto! / Incorrecto: El albarán debe coincidir con la mercancía recibida para que la documentación es correcta. | G22: ='Cont-Obj'!E:E -> 3.4 Recepción de materias primas
A23: ='Cont-Obj'!A:A -> Módulo 4. Conservación y control de temperaturas | B23: ='Cont-Obj'!B:B -> O4.1 Explicar cómo influye la temperatura en la seguridad de los alimentos y describir la importancia de mantener la cadena de frío durante su manipulación y conservación. | C23: ='Cont-Obj'!C:C -> 19 | E23: Leer texto | G23: ='Cont-Obj'!E:E -> 4.1 ¿Por qué es tan importante la temperatura?
A24: ='Cont-Obj'!A:A -> Módulo 4. Conservación y control de temperaturas | B24: ='Cont-Obj'!B:B -> O4.2 Mantener los alimentos a temperaturas adecuadas durante su conservación. | C24: ='Cont-Obj'!C:C -> 20 | E24: Título de la actividad: Frío bajo control Enunciado: Acabas de recibir varios productos que necesitan conservarse en frío y debes almacenarlos correctamente antes de continuar con tu trabajo. Explora la zona de recepción, el refrigerador y el congelador. Pulsa sobre los productos, las puertas, los indicadores de temperatura y todo lo que necesites para comprobar que las condiciones de almacenamiento son seguras. En la checklist de la derecha tienes las tareas que debes completar. Se marcarán a medida que las resuelvas. Cada producto, cada puerta y cada temperatura importan. ¡Demuestra que tienes el frío bajo control!" Descripción: Actividad interactiva de inspección. El alumnado debe organizar la recepción y el almacenamiento de productos refrigerados y congelados, comprobando que se cumplen las condiciones necesarias para conservarlos de forma segura. Existirán 3 escenas diferentes: 1. Escena de recepción: Se visualizan en una mesa todos los productos que se deben almacenar. 2. Escena de congelación: los productos que deben ser congelados aparecerán en un cajón a la izquierda y habrá un congelador a la derecha con su puerta, su indicador de temperatura y sus estantes interiores. 3. Escena de refrigeración: los productos que deben ser refrigerados aparecerán en un cajón a la izquierda y habrá un refrigerador a la derecha con su puerta, su indicador de temperatura y sus estantes interiores. Además, una Checklist lateral (esquina superior derecha) disponible en todas las escenas con items que se van marcando a medida que se completan. El alumnado interactúa pulsando directamente sobre los elementos de la escena: al hacerlo, se produce una transición de escena (zoom al elemento, primer plano, vista interior del equipo...) y aparece la información o la acción correspondiente. Si toma una decisión incorrecta, recibe un feedback inmediato. La actividad termina cuando todos los productos están almacenados correctamente, las incidencias se han gestionado y la checklist está completa. Checklist lateral: ☐ Clasificar los productos según su conservación. ☐ Comprobar la temperatura del refrigerador (rango correcto ≤ 4 °C). ☐ Comprobar la temperatura del congelador (rango correcto ≤ -18 °C). ☐ Introducir los productos refrigerados. ☐ Introducir los productos congelados. ☐ Resolver la elaboración caliente. ☐ Revisar los productos congelados descongelados. ☐ Organizar la carga del equipo de refrigeración. ☐ Organizar la carga del equipo de congelación. 1. Escena de recepcion Elementos interactivos (productos encima de la mesa): leche fresca (envase de cartón con 6 uds), yogures (2 pack de 4), salmón (bandeja con film), carne picada (bandeja con film), pollo congelado (2 tupper), verduras congeladas (3 bolsas), helado (2 tarrinas), una olla con guiso recién cocinado (elaboración caliente) y una dorada con signos de descongelación (escarcha). Cómo interactúa el alumnado: el alumnado pulsa cada producto de la mesa. Al pulsarlo, se produce una transición de escena: el producto se amplía en primer plano y aparece una pregunta: "¿Dónde debe conservarse este producto?" con dos opciones: Refrigerador o Congelador. - Si acierta, el producto se marca como clasificado y vuelve a la mesa con un icono de verificación. - Si falla, aparece el feedback de sistema de conservación incorrecto. (1) Al pulsar la olla con guiso aparece un mensaje :"Ojo, se trata de una elaboración caliente, un guiso recien cocinado". Y la pregunta que aparece a continuación es: "¿Cómo debes conservar esta elaboración?" con opciones: Introducirla directamente en el refrigerador / Enfriarla antes de conservarla. - Si acierta (enfriarla), aparece el mensaje "Producto gestionado" y la olla desaparecerá de la mesa. - Si falla, feedback de riesgo para la conservación. (2) Al pulsar la dorada con signos de descongelación aparece un mensaje: "Ojo, este producto tiene signos de descongelación y supone un riesgo". Y la pregunta que aparece es: "¿Qué haces con este producto?" con opciones: Volver a congelarlo directamente / Comunicar incidencia y seguir el procedimiento. - Si acierta (comunicar incidencia), aparece el mensaje "Producto gestionado" y la dorada desaparecerá de la mesa. - Si falla, feedback de producto descongelado. (3) Tras superar esta escena se marcarán como completadas los siguientes items de la checklist: ☐ Clasificar los productos según su conservación. ☐ Resolver la elaboración caliente. ☐ Revisar los productos congelados descongelados. Antes de pasar a la siguiente escena, en el centro de la pantalla aparecerá una pregunta: "¿Cuál es el siguiente paso?" con opciones: Ir a la zona de refrigeracion/Ir a la zona de congelación. - Si acierta (zona de congelación), aparece el feedback de acierto. (4) - Si falla, aparece el feedback de error. (5) 2. Escena de congelación Elementos interactivos: - Congelador: puerta con tirador, indicador digital de temperatura y estantes interiores visibles al abrirlo. - Productos clasificados para congelar: 2 tuppers de pollo, 3 bolsas de verduras y 2 tarrinas de helado. Cómo interactúa el alumnado: el alumnado pulsa el indicador de temperatura del congelador. Se produce una transición de escena: zoom al indicador, que marca -18 °C (correcto). Al pulsarlo, aparece "Temperatura correcta. Puedes utilizar el equipo" y se quita el zoom para volver a la escena. Después pulsa la puerta del congelador. Se abre y se visualiza el interior del equipo y un temporizador visual (barra que se va vaciando). El alumnado debe arrastrar los productos congelados a los estantes. - Si introduce todos los productos y pulsa la puerta para cerrarla antes de que la barra se vacíe, saldrá el mensaje "Buena actuación, productos correctamente almacenados". - Si la barra de tiempo se consume: aparece el feedback de pérdida de frío. (6) Los productos deben estar bien colocados en los estantes siguiendo los siguientes criterios: - En el primer estante van las bolsas de verduras. Caben 8 bolsas, 4 izq y 4 drch. A la izquierda hay 4 y a la derecha 1, por lo que las 3 que debe colocar irán en el lado derecho. - En el segundo estante van las tarrinas de helado y está vacío. Caben 4 tarrinas, 2 izq y 2 drch. Las 2 que debe colcoar irán a su gusto, siempre que sea en ese estante. - En el tercer estante van los tuppers de pollo. Caben 8, 4 izq y 4 drch. A la derecha hay 3, por lo que los 2 que debe colocar pueden ir a la izq o 1 a la izq y otro a la drch. Si cierra la nevera y la colocación no es correcta saltará el feedback de error (7) y deberá probar de nuevo. Tras superar esta escena se marcarán como completadas los siguientes items de la checklist: ☐ Comprobar la temperatura del congelador (rango correcto ≤ -18 °C). ☐ Introducir los productos congelados. ☐ Organizar la carga del equipo de congelación. 3. Escena de refrigeración Elementos interactivos: - Refrigerador: puerta con tirador, indicador digital de temperatura y estantes interiores visibles al abrirlo. - Productos clasificados para refrigerar: 6 cartones de leche fresca, 2 packs de 4 yogures, 1 bandeja de salmón y 1 bandeja de carne picada. Cómo interactúa el alumnado: el alumnado pulsa el indicador de temperatura del refrigerador. Se produce una transición de escena: zoom al indicador, que marca 8 °C. Aparece un mensaje: "Temperatura fuera del rango establecido (≤4 °C). ¿Qué haces?" con opciones: Continuar igualmente / Comunicar incidencia. - Si acierta (comunicar incidencia), aparece el mensaje "Incidencia gestionada" y el indicador se reestablece a 4 ºC. - Si falla, feedback de temperatura fuera de condiciones. (8) Después pulsa la puerta del refrigerador. Se abre y se visualiza el interior del equipo y un temporizador visual (barra que se va vaciando). El alumnado debe arrastrar los productos a los estantes. - Si introduce todos los productos y pulsa la puerta para cerrarla antes de que la barra se vacíe, saldrá el mensaje "Buena actuación, productos correctamente almacenados". - Si deja la puerta abierta y pulsa otra cosa: aparece el feedback de pérdida de frío. (6) Los productos deben estar bien colocados en los estantes siguiendo los siguientes criterios: - En el primer estante va leche a la izq y yogures a la drch. Caben 4 cartones de leche y 4 packs de yogures. A la izquierda hay 2 cartones de leche y a la derecha 3 packs de yogures, por lo que el alumnado debe colocar 2 cartones de leche a la izq y 1 pack de yogurt a la drch. - En el segundo estante (igual que el primero) va leche a la izq y yogures a la drch. Caben 4 cartones de leche y 4 packs de yogures. La parte izquierda está vacía por lo que coloca los 4 cartones de leche que le quedan y a la derecha hay 3 packs de yogures, por lo que coloca el pack de yogurt que le queda. - En el tercer estante van las bandejas de salmón a la izq y las de carne a la drch. Caben 4 de cada una. A la izq hay 2 de salmón, por lo que pone encima la unica que tiene. La drcha está vacía, donde va la de carne. Si cierra la nevera y la colocación no es correcta saltará el feedback de error (7) y deberá probar de nuevo. Tras superar esta escena se marcarán como completadas los siguientes items de la checklist: ☐ Comprobar la temperatura del refrigerador (rango correcto ≤ 4 °C). ☐ Introducir los productos refrigerados. ☐ Organizar la carga del equipo de refrigeración. Finalización de la actividad: Cuando todos los productos están clasificados, los equipos comprobados, las situaciones resueltas y los productos almacenados correctamente, la checklist se completa y aparece el mensaje final: "✓ Frío bajo control. Has clasificado y almacenado los productos correctamente, controlado las condiciones de los equipos y resuelto las incidencias planteadas para mantener la conservación segura de los alimentos." | F24: 1. "Sistema de conservación incorrecto. Este producto necesita unas condiciones de conservación diferentes. Revisa si debe mantenerse refrigerado o congelado y colócalo en el equipo correspondiente." 2. "Riesgo para la conservación de los demás alimentos. Introducir una gran cantidad de alimento muy caliente puede elevar la temperatura de la cámara y poner en riesgo la conservación segura de los demás productos. Sigue el procedimiento establecido para enfriar la elaboración de forma segura antes de conservarla." 3. "Comprueba las condiciones del producto. No debes volver a congelar directamente un alimento que presenta signos de descongelación. Sigue el procedimiento establecido para determinar si puede utilizarse o si debe descartarse." 4. "Actuación correcta. Has clasificado los productos y ahora debes comprobar las condiciones del congelador antes de almacenarlos. Priorizar los productos congelados es lo adecuado, ya que requieren condiciones de conservación más exigentes y es importante comprobar cuanto antes que se mantienen dentro de los límites establecidos." 5. "Revisa tu decisión. Antes de almacenar los productos, conviene atender primero los productos congelados, ya que necesitan condiciones de conservación más exigentes y es prioritario comprobar que no han perdido la cadena de frío. Comienza por la zona de congelación y continúa después con la de refrigeración." 6. "Pérdida de frío. Mantener la puerta abierta innecesariamente favorece el intercambio de aire y dificulta mantener la temperatura adecuada. Introduce los productos con agilidad y cierra la puerta a tiempo." 7. "Equipo desorganízado. Has introducido los productos de forma incorrecta. El equipo debe estar ordenado para coseguir fluidez en el trabajo. Reorganíza la mercancía." 8. "Temperatura fuera de las condiciones establecidas. La temperatura del equipo no se encuentra dentro de los límites establecidos. No continúes almacenando productos y comunica la incidencia siguiendo el procedimiento del establecimiento." Actividad completada: ✓ Frío bajo control. Has clasificado y almacenado los productos correctamente, controlado las condiciones de los equipos y resuelto las incidencias planteadas para mantener la conservación segura de los alimentos. | G24: ='Cont-Obj'!E:E -> 4.2 Refrigeración y congelación
A25: ='Cont-Obj'!A:A -> Módulo 4. Conservación y control de temperaturas | B25: ='Cont-Obj'!B:B -> O4.2 Mantener los alimentos a temperaturas adecuadas durante su conservación. | C25: ='Cont-Obj'!C:C -> 20 | E25: Título de la actividad: Frío bajo control Enunciado: Acabas de recibir varios productos que necesitan conservarse en frío y debes almacenarlos correctamente antes de continuar con tu trabajo. Explora la zona de recepción, el refrigerador y el congelador. Pulsa sobre los productos, las puertas, los indicadores de temperatura y todo lo que necesites para comprobar que las condiciones de almacenamiento son seguras. En la checklist de la derecha tienes las tareas que debes completar. Se marcarán a medida que las resuelvas. Cada producto, cada puerta y cada temperatura importan. ¡Demuestra que tienes el frío bajo control!" Descripción: Actividad interactiva de inspección. El alumnado debe organizar la recepción y el almacenamiento de productos refrigerados y congelados, comprobando que se cumplen las condiciones necesarias para conservarlos de forma segura. Existirán 3 escenas diferentes: 1. Escena de recepción: Se visualizan en una mesa todos los productos que se deben almacenar. 2. Escena de congelación: los productos que deben ser congelados aparecerán en un cajón a la izquierda y habrá un congelador a la derecha con su puerta, su indicador de temperatura y sus estantes interiores. 3. Escena de refrigeración: los productos que deben ser refrigerados aparecerán en un cajón a la izquierda y habrá un refrigerador a la derecha con su puerta, su indicador de temperatura y sus estantes interiores. Además, una Checklist lateral (esquina superior derecha) disponible en todas las escenas con items que se van marcando a medida que se completan. El alumnado interactúa pulsando directamente sobre los elementos de la escena: al hacerlo, se produce una transición de escena (zoom al elemento, primer plano, vista interior del equipo...) y aparece la información o la acción correspondiente. Si toma una decisión incorrecta, recibe un feedback inmediato. La actividad termina cuando todos los productos están almacenados correctamente, las incidencias se han gestionado y la checklist está completa. Checklist lateral: ☐ Clasificar los productos según su conservación. ☐ Comprobar la temperatura del refrigerador (rango correcto ≤ 4 °C). ☐ Comprobar la temperatura del congelador (rango correcto ≤ -18 °C). ☐ Introducir los productos refrigerados. ☐ Introducir los productos congelados. ☐ Resolver la elaboración caliente. ☐ Revisar los productos congelados descongelados. ☐ Organizar la carga del equipo de refrigeración. ☐ Organizar la carga del equipo de congelación. 1. Escena de recepcion Elementos interactivos (productos encima de la mesa): leche fresca (envase de cartón con 6 uds), yogures (2 pack de 4), salmón (bandeja con film), carne picada (bandeja con film), pollo congelado (2 tupper), verduras congeladas (3 bolsas), helado (2 tarrinas), una olla con guiso recién cocinado (elaboración caliente) y una dorada con signos de descongelación (escarcha). Cómo interactúa el alumnado: el alumnado pulsa cada producto de la mesa. Al pulsarlo, se produce una transición de escena: el producto se amplía en primer plano y aparece una pregunta: "¿Dónde debe conservarse este producto?" con dos opciones: Refrigerador o Congelador. - Si acierta, el producto se marca como clasificado y vuelve a la mesa con un icono de verificación. - Si falla, aparece el feedback de sistema de conservación incorrecto. (1) Al pulsar la olla con guiso aparece un mensaje :"Ojo, se trata de una elaboración caliente, un guiso recien cocinado". Y la pregunta que aparece a continuación es: "¿Cómo debes conservar esta elaboración?" con opciones: Introducirla directamente en el refrigerador / Enfriarla antes de conservarla. - Si acierta (enfriarla), aparece el mensaje "Producto gestionado" y la olla desaparecerá de la mesa. - Si falla, feedback de riesgo para la conservación. (2) Al pulsar la dorada con signos de descongelación aparece un mensaje: "Ojo, este producto tiene signos de descongelación y supone un riesgo". Y la pregunta que aparece es: "¿Qué haces con este producto?" con opciones: Volver a congelarlo directamente / Comunicar incidencia y seguir el procedimiento. - Si acierta (comunicar incidencia), aparece el mensaje "Producto gestionado" y la dorada desaparecerá de la mesa. - Si falla, feedback de producto descongelado. (3) Tras superar esta escena se marcarán como completadas los siguientes items de la checklist: ☐ Clasificar los productos según su conservación. ☐ Resolver la elaboración caliente. ☐ Revisar los productos congelados descongelados. Antes de pasar a la siguiente escena, en el centro de la pantalla aparecerá una pregunta: "¿Cuál es el siguiente paso?" con opciones: Ir a la zona de refrigeracion/Ir a la zona de congelación. - Si acierta (zona de congelación), aparece el feedback de acierto. (4) - Si falla, aparece el feedback de error. (5) 2. Escena de congelación Elementos interactivos: - Congelador: puerta con tirador, indicador digital de temperatura y estantes interiores visibles al abrirlo. - Productos clasificados para congelar: 2 tuppers de pollo, 3 bolsas de verduras y 2 tarrinas de helado. Cómo interactúa el alumnado: el alumnado pulsa el indicador de temperatura del congelador. Se produce una transición de escena: zoom al indicador, que marca -18 °C (correcto). Al pulsarlo, aparece "Temperatura correcta. Puedes utilizar el equipo" y se quita el zoom para volver a la escena. Después pulsa la puerta del congelador. Se abre y se visualiza el interior del equipo y un temporizador visual (barra que se va vaciando). El alumnado debe arrastrar los productos congelados a los estantes. - Si introduce todos los productos y pulsa la puerta para cerrarla antes de que la barra se vacíe, saldrá el mensaje "Buena actuación, productos correctamente almacenados". - Si la barra de tiempo se consume: aparece el feedback de pérdida de frío. (6) Los productos deben estar bien colocados en los estantes siguiendo los siguientes criterios: - En el primer estante van las bolsas de verduras. Caben 8 bolsas, 4 izq y 4 drch. A la izquierda hay 4 y a la derecha 1, por lo que las 3 que debe colocar irán en el lado derecho. - En el segundo estante van las tarrinas de helado y está vacío. Caben 4 tarrinas, 2 izq y 2 drch. Las 2 que debe colcoar irán a su gusto, siempre que sea en ese estante. - En el tercer estante van los tuppers de pollo. Caben 8, 4 izq y 4 drch. A la derecha hay 3, por lo que los 2 que debe colocar pueden ir a la izq o 1 a la izq y otro a la drch. Si cierra la nevera y la colocación no es correcta saltará el feedback de error (7) y deberá probar de nuevo. Tras superar esta escena se marcarán como completadas los siguientes items de la checklist: ☐ Comprobar la temperatura del congelador (rango correcto ≤ -18 °C). ☐ Introducir los productos congelados. ☐ Organizar la carga del equipo de congelación. 3. Escena de refrigeración Elementos interactivos: - Refrigerador: puerta con tirador, indicador digital de temperatura y estantes interiores visibles al abrirlo. - Productos clasificados para refrigerar: 6 cartones de leche fresca, 2 packs de 4 yogures, 1 bandeja de salmón y 1 bandeja de carne picada. Cómo interactúa el alumnado: el alumnado pulsa el indicador de temperatura del refrigerador. Se produce una transición de escena: zoom al indicador, que marca 8 °C. Aparece un mensaje: "Temperatura fuera del rango establecido (≤4 °C). ¿Qué haces?" con opciones: Continuar igualmente / Comunicar incidencia. - Si acierta (comunicar incidencia), aparece el mensaje "Incidencia gestionada" y el indicador se reestablece a 4 ºC. - Si falla, feedback de temperatura fuera de condiciones. (8) Después pulsa la puerta del refrigerador. Se abre y se visualiza el interior del equipo y un temporizador visual (barra que se va vaciando). El alumnado debe arrastrar los productos a los estantes. - Si introduce todos los productos y pulsa la puerta para cerrarla antes de que la barra se vacíe, saldrá el mensaje "Buena actuación, productos correctamente almacenados". - Si deja la puerta abierta y pulsa otra cosa: aparece el feedback de pérdida de frío. (6) Los productos deben estar bien colocados en los estantes siguiendo los siguientes criterios: - En el primer estante va leche a la izq y yogures a la drch. Caben 4 cartones de leche y 4 packs de yogures. A la izquierda hay 2 cartones de leche y a la derecha 3 packs de yogures, por lo que el alumnado debe colocar 2 cartones de leche a la izq y 1 pack de yogurt a la drch. - En el segundo estante (igual que el primero) va leche a la izq y yogures a la drch. Caben 4 cartones de leche y 4 packs de yogures. La parte izquierda está vacía por lo que coloca los 4 cartones de leche que le quedan y a la derecha hay 3 packs de yogures, por lo que coloca el pack de yogurt que le queda. - En el tercer estante van las bandejas de salmón a la izq y las de carne a la drch. Caben 4 de cada una. A la izq hay 2 de salmón, por lo que pone encima la unica que tiene. La drcha está vacía, donde va la de carne. Si cierra la nevera y la colocación no es correcta saltará el feedback de error (7) y deberá probar de nuevo. Tras superar esta escena se marcarán como completadas los siguientes items de la checklist: ☐ Comprobar la temperatura del refrigerador (rango correcto ≤ 4 °C). ☐ Introducir los productos refrigerados. ☐ Organizar la carga del equipo de refrigeración. Finalización de la actividad: Cuando todos los productos están clasificados, los equipos comprobados, las situaciones resueltas y los productos almacenados correctamente, la checklist se completa y aparece el mensaje final: "✓ Frío bajo control. Has clasificado y almacenado los productos correctamente, controlado las condiciones de los equipos y resuelto las incidencias planteadas para mantener la conservación segura de los alimentos." | F25: 1. "Sistema de conservación incorrecto. Este producto necesita unas condiciones de conservación diferentes. Revisa si debe mantenerse refrigerado o congelado y colócalo en el equipo correspondiente." 2. "Riesgo para la conservación de los demás alimentos. Introducir una gran cantidad de alimento muy caliente puede elevar la temperatura de la cámara y poner en riesgo la conservación segura de los demás productos. Sigue el procedimiento establecido para enfriar la elaboración de forma segura antes de conservarla." 3. "Comprueba las condiciones del producto. No debes volver a congelar directamente un alimento que presenta signos de descongelación. Sigue el procedimiento establecido para determinar si puede utilizarse o si debe descartarse." 4. "Actuación correcta. Has clasificado los productos y ahora debes comprobar las condiciones del congelador antes de almacenarlos. Priorizar los productos congelados es lo adecuado, ya que requieren condiciones de conservación más exigentes y es importante comprobar cuanto antes que se mantienen dentro de los límites establecidos." 5. "Revisa tu decisión. Antes de almacenar los productos, conviene atender primero los productos congelados, ya que necesitan condiciones de conservación más exigentes y es prioritario comprobar que no han perdido la cadena de frío. Comienza por la zona de congelación y continúa después con la de refrigeración." 6. "Pérdida de frío. Mantener la puerta abierta innecesariamente favorece el intercambio de aire y dificulta mantener la temperatura adecuada. Introduce los productos con agilidad y cierra la puerta a tiempo." 7. "Equipo desorganízado. Has introducido los productos de forma incorrecta. El equipo debe estar ordenado para coseguir fluidez en el trabajo. Reorganíza la mercancía." 8. "Temperatura fuera de las condiciones establecidas. La temperatura del equipo no se encuentra dentro de los límites establecidos. No continúes almacenando productos y comunica la incidencia siguiendo el procedimiento del establecimiento." Actividad completada: ✓ Frío bajo control. Has clasificado y almacenado los productos correctamente, controlado las condiciones de los equipos y resuelto las incidencias planteadas para mantener la conservación segura de los alimentos. | G25: ='Cont-Obj'!E:E -> 4.5 Mantenimiento de los alimentos y servicio
A26: ='Cont-Obj'!A:A -> Módulo 4. Conservación y control de temperaturas | B26: ='Cont-Obj'!B:B -> O4.3 Conocer procedimientos seguros de descongelación. | C26: ='Cont-Obj'!C:C -> 21 | E26: Leer texto | F26: Descongelar de forma segura Cuando descongelas un alimento, es importante evitar que permanezca demasiado tiempo a temperaturas que favorezcan la multiplicación de microorganismos. - En el frigorífico: es una de las opciones más seguras. Protege el alimento y evita que sus jugos goteen sobre otros productos. - En el microondas: puede ser útil cuando necesitas descongelar un alimento rápidamente, pero debes cocinarlo inmediatamente después. - A temperatura ambiente: no dejes alimentos descongelándose durante horas sobre una encimera o cerca de una fuente de calor. - Después de descongelar: manipula y conserva el alimento según las condiciones adecuadas para ese producto. Cada situación es diferente. Antes de actuar, piensa qué necesita el alimento, cuánto tiempo tienes y cómo puedes mantenerlo seguro. | G26: ='Cont-Obj'!E:E -> 4.3 Descongelación segura
A27: ='Cont-Obj'!A:A -> Módulo 4. Conservación y control de temperaturas | B27: ='Cont-Obj'!B:B -> O4.4 Aplicar procedimientos seguros de descongelación. | C27: ='Cont-Obj'!C:C -> 22 | E27: Título de la actividad: Descongelación: el reto del encargado. Enunciado: El encargado del restaurante necesita que te ocupes de varios alimentos antes y durante el servicio. Cada uno presenta una situación diferente y tendrás que decidir cómo actuar para mantenerlos en condiciones seguras. Explora la cocina, interactúa con los objetos y toma tus propias decisiones. Cuando consideres que has terminado, pulsa el icono del timbre para avisar al encargado. Si algo no está bien, recibirás una pista que te ayudará a revisar lo que has hecho. ¡Demuestra que sabes descongelar con criterio! Descripción: Actividad interactiva de simulación en la que el alumnado debe resolver dos situaciones relacionadas con la descongelación de alimentos en una cocina de restaurante. El encargado transmite sus indicaciones mediante texto en la parte superior de la pantalla. El alumnado explora la cocina, interactúa directamente con los objetos y toma sus propias decisiones. Cuando considera que ha terminado, pulsa el icono del timbre. El sistema comprueba el estado final de la escena y las acciones realizadas. Si la resolución es adecuada, la actividad avanza; si hay algún error, aparece un feedback y el alumnado puede volver a la escena para corregirlo. Se trabajan los métodos seguros de descongelación y las decisiones posteriores según el contexto (con antelación o con urgencia). Elementos de la pantalla: - Instrucciones del encargado: texto en la parte superior que contextualiza cada situación y explica qué necesita el restaurante. - La cocina incluye todos estos objetos interactivos: congelador, frigorífico, pila de bandejas al lado del frigorífico, encimera, microondas, zona de cocción y los productos a manipular según la indicación del encargado. - Objetos interactivos: al pasar el cursor por encima, se resaltan para indicar que pueden seleccionarse. El alumnado puede explorar, seleccionar, abrir, mover y colocar objetos. - Icono del timbre: esquina superior derecha, separado visualmente. Se pulsa cuando el alumnado considere que ha terminado. Situación 1: Pollo para el servicio Indicación del encargado (texto en pantalla): «Mañana tenemos pollo al curry en el menú y necesitamos dejar el pollo preparado con antelación. Está en el congelador. ¿Puedes encargarte de ello? Avísame cuando hayas terminado». Qué hace el alumnado: Paso 1. Pulsa sobre el congelador. Se abre y aparece el pollo congelado en su interior. Paso 2. Selecciona el pollo y lo retira del congelador. Paso 3. Decide dónde colocarlo para que se descongele. Opciones disponibles: - Dejarlo en la encimera (incorrecto: descongelación a temperatura ambiente). - Colocarlo cerca de una fuente de calor (incorrecto: favorece la multiplicación de microorganismos). - Llevarlo al frigorífico (correcto). Paso 4. Si elige el frigorífico, debe decidir cómo colocar el pollo: - ¿Sobre una bandeja o recipiente que contenga sus jugos? (correcto). - ¿Directamente sobre el estante, sin protección? (incorrecto: los jugos pueden gotear sobre otros alimentos). - ¿En qué altura del frigorífico? (debe colocarse abajo del todo). Paso 5. Puede revisar y modificar sus decisiones antes de pulsar el timbre. Paso 6. Pulsa el icono del timbre para que el sistema evalúe la resolución. Resolución esperada: El pollo debe descongelarse en el frigorífico, sobre una bandeja que contenga sus jugos y colocado abajo del todo, de forma que no pueda gotear sobre otros alimentos. Situación 2: Salmón para una comanda urgente Indicación del encargado (texto en pantalla): «¡Tenemos una comanda de salmón y lo necesitamos para preparar el plato ahora! El que queda está congelado. ¿Puedes solucionarlo? Avísame cuando esté listo». Qué hace el alumnado: Paso 1. Pulsa sobre el congelador. Se abre y aparece el salmón congelado. Paso 2. Decide cómo actuar teniendo en cuenta que el restaurante necesita el alimento para preparar una comanda en ese momento. Opciones: - Llevarlo al frigorífico (seguro, pero no resuelve la urgencia). - Dejarlo sobre la encimera (incorrecto: descongelación a temperatura ambiente). - Utilizar el microondas (correcto para responder a la urgencia). Paso 3. Si elige el microondas, debe abrirlo y colocar el salmón en su interior. Paso 4. Cuando termine el proceso, debe decidir qué hacer con el salmón. Opciones: - Llevarlo directamente a la zona de cocción (correcto: el alimento descongelado en microondas debe cocinarse inmediatamente después). - Guardarlo para utilizarlo más tarde (incorrecto). - Dejarlo en la encimera (incorrecto). Paso 5. Pulsa el icono del timbre para que el sistema evalúe la resolución. Resolución esperada: Para responder a la urgencia, el alumnado puede utilizar el microondas para descongelar el salmón y debe cocinarlo inmediatamente después. Mensaje de cierre (al completar las dos situaciones): «Buen trabajo. Hoy has tenido que decidir cómo descongelar distintos alimentos, qué hacer después de utilizar el microondas y cómo actuar ante una descongelación inadecuada. Recuerda que no basta con elegir un método: también debes mantener los alimentos en condiciones seguras y actuar cuando detectes una práctica que pueda comprometer su seguridad». | F27: Feedback de la Situación 1 (pollo): Descongelar el pollo en la encimera (incorrecto): Descongelación insegura. Dejar el pollo a temperatura ambiente durante horas favorece la multiplicación de microorganismos. Descongélalo en el frigorífico para mantenerlo en condiciones seguras. Descongelar el pollo cerca de una fuente de calor (incorrecto): Descongelación insegura. El calor acelera la multiplicación de microorganismos en la superficie del alimento. Descongela el pollo en el frigorífico. Descongelar el pollo en el frigorífico, pero sin bandeja (incorrecto): Colocación insegura. Los jugos del pollo crudo pueden gotear sobre otros alimentos y contaminarlos. Colócalo sobre una bandeja o recipiente que contenga sus jugos. Descongelar el pollo en el frigorífico, con bandeja, pero no abajo del todo (incorrecto): Colocación insegura. Aunque el pollo esté sobre una bandeja, si no está en la zona inferior del frigorífico sus jugos podrían caer sobre otros alimentos. Colócalo siempre abajo del todo. Descongelar el pollo correctamente (correcto): ✓ Descongelación correcta. Has descongelado el pollo en el frigorífico, sobre una bandeja que contiene sus jugos y colocado en la zona inferior, evitando que pueda contaminar otros alimentos. Feedback de la Situación 2 (salmón): Descongelar el salmón en el frigorífico (incorrecto, no resuelve la urgencia): La refrigeración es un método seguro de descongelación, pero no resuelve la necesidad inmediata de la comanda. Descongelar el salmón en la encimera (incorrecto): Descongelación insegura. Dejar el salmón a temperatura ambiente favorece la multiplicación de microorganismos. No es un método adecuado, y menos para una comanda urgente. Descongelar el salmón en el microondas y guardarlo para más tarde (incorrecto): Actuación insegura. El alimento descongelado en el microondas debe cocinarse inmediatamente después. Si lo guardas o lo dejas esperando, puedes comprometer su seguridad. Descongelar el salmón en el microondas y dejarlo en la encimera (incorrecto): Actuación insegura. El alimento descongelado en el microondas debe cocinarse inmediatamente después. Dejarlo en la encimera favorece la multiplicación de microorganismos. Descongelar el salmón en el microondas y cocinarlo inmediatamente (correcto): ✓ Descongelación correcta. Has utilizado el microondas para responder a la urgencia y has cocinado el salmón inmediatamente después, tal como exige este método. Si el alumnado pulsa el timbre sin haber resuelto la situación (error general): Aún queda algo por resolver. Revisa la escena: ¿has descongelado el alimento? ¿Has decidido qué hacer con él después? Corrige lo que sea necesario antes de avisar al encargado. | G27: ='Cont-Obj'!E:E -> 4.3 Descongelación segura
A28: ='Cont-Obj'!A:A -> Módulo 4. Conservación y control de temperaturas | B28: ='Cont-Obj'!B:B -> O4.5 Aplicar correctamente los procedimientos de cocinado, enfriamiento y recalentamiento de los alimentos para mantener su seguridad durante su preparación y conservación. | C28: ='Cont-Obj'!C:C -> 23 | E28: Leer texto | G28: ='Cont-Obj'!E:E -> 4.4 Cocinado, enfriamiento y recalentamiento
A29: ='Cont-Obj'!A:A -> Módulo 4. Conservación y control de temperaturas | B29: ='Cont-Obj'!B:B -> O4.5 Aplicar correctamente los procedimientos de cocinado, enfriamiento y recalentamiento de los alimentos para mantener su seguridad durante su preparación y conservación. | C29: ='Cont-Obj'!C:C -> 24 | E29: Vas a preparar una elaboración que no se va a consumir inmediatamente y tendrás que gestionar correctamente todo el proceso: cocinarla, enfriarla, conservarla y, posteriormente, recalentarla. La actividad se desarrolla como una secuencia de decisiones. En cada fase aparecerán diferentes opciones y tendrás que seleccionar la actuación adecuada antes de pasar a la siguiente. Deberás prestar especial atención a las condiciones de cocinado, a la forma de enfriar el alimento y a cómo debe realizarse el recalentamiento. Fase 1 — Cocinado Tienes los ingredientes preparados y debes cocinar la elaboración. Se presentan diferentes opciones: - Cocinar siguiendo el procedimiento establecido para ese alimento. → Correcto. - Interrumpir la cocción antes de alcanzar las condiciones necesarias y continuar más tarde sin seguir el procedimiento establecido. → Incorrecto. - Asegurarte de que el alimento alcanza las condiciones necesarias de tiempo y temperatura según el procedimiento establecido. → Correcto. El objetivo es que entiendas que cocinar correctamente ayuda a eliminar muchos de los microorganismos que pueden estar presentes en los alimentos. Fase 2 — Preparar el enfriamiento La elaboración ya está cocinada, pero no se va a consumir inmediatamente. Debes decidir cómo prepararla para su conservación. Aparecen diferentes posibilidades: - Introducir una gran cantidad de alimento muy caliente directamente en el frigorífico. → Incorrecto. - Dividir la elaboración en recipientes adecuados y poco profundos para favorecer un enfriamiento más rápido. → Correcto. - Dejar el alimento sin protección mientras se enfría. → Incorrecto. - Una vez enfriado, protegerlo, identificarlo y conservarlo en las condiciones establecidas. → Correcto. Fase 3 — Recalentamiento Posteriormente, debes preparar la elaboración para servirla. Se presentan diferentes opciones: - Recalentar el alimento de forma completa y uniforme antes de servirlo. → Correcto. - Calentar únicamente una parte del alimento y servirlo cuando todavía existen zonas sin recalentar adecuadamente. → Incorrecto. - Recalentar repetidamente el mismo alimento cada vez que sea necesario servirlo. → Incorrecto. - Evitar conservar durante demasiado tiempo un alimento que ya ha sido recalentado. → Correcto. La actividad termina cuando completas correctamente las tres fases. | F29: Cuando el alumno acierte una decisión: ¡Correcto! Has elegido una práctica adecuada para mantener la seguridad del alimento durante esta fase del proceso. Cuando el alumno falle durante el cocinado: No es correcto. La cocción debe realizarse siguiendo el procedimiento establecido y asegurando que el alimento alcanza las condiciones necesarias de tiempo y temperatura. Cuando el alumno introduzca una gran cantidad de alimento caliente en el frigorífico: No es correcto. Una gran cantidad de alimento muy caliente puede aumentar la temperatura del equipo y afectar a otros alimentos. Debes favorecer un enfriamiento seguro antes de conservarlo. Cuando el alumno elija correctamente los recipientes: ¡Correcto! Utilizar recipientes adecuados y poco profundos favorece un enfriamiento más rápido. Cuando el alumno deje el alimento sin proteger o identificar: No es correcto. Una vez enfriado, el alimento debe protegerse, identificarse y conservarse en las condiciones establecidas. Cuando el alumno recaliente correctamente: ¡Correcto! El alimento debe recalentarse de forma completa y uniforme antes de servirlo. Cuando el alumno recaliente repetidamente: No es correcto. No se recomienda recalentar repetidamente un mismo alimento. Además, debe evitarse conservar durante demasiado tiempo un alimento que ya ha sido recalentado. | G29: ='Cont-Obj'!E:E -> 4.4 Cocinado, enfriamiento y recalentamiento
A30: ='Cont-Obj'!A:A -> Módulo 4. Conservación y control de temperaturas | B30: ='Cont-Obj'!B:B -> O4.6 Mantener los alimentos en condiciones adecuadas de temperatura durante su conservación y servicio. | C30: ='Cont-Obj'!C:C | G30: ='Cont-Obj'!E:E -> 4.5 Mantenimiento de los alimentos y servicio
A31: ='Cont-Obj'!A:A -> Módulo 4. Conservación y control de temperaturas | B31: ='Cont-Obj'!B:B -> O4.7 Organizar correctamente los alimentos en cámaras y almacenes para favorecer su conservación y evitar contaminaciones. | C31: ='Cont-Obj'!C:C -> 25 | E31: Título de la actividad: Cada cosa en su lugar. Enunciado: Debido al volumen de trabajo acumulado durante la mañana y a la falta de personal, nadie ha tenido tiempo de ordenar el almacén. Como consecuencia, hay productos mezclados, alimentos fuera de su sitio, recipientes abiertos y productos de limpieza junto a la comida. El encargado te pide ayuda para dejarlo todo organizado antes de continuar con el servicio. Explora la escena y arrastra cada cosa a su lugar, tú decides qué está mal colocado y dónde debería ir. Cuando todo esté en su sitio, el almacén estará listo. ¡Demuestra que sabes poner cada cosa en su lugar! Descripción: Actividad interactiva de exploración y organización. El almacén de un restaurante está completamente desordenado y el encargado pide al alumnado que deje el almacén organizado antes de continuar el servicio. El alumnado explora libremente la escena e interactúa con cualquier objeto: no hay checklist, no hay pistas visuales, no hay objetos resaltados. Debe descubrir por sí mismo qué está mal colocado y arrastrar cada producto a su lugar correspondiente. La actividad se centra en ordenar el desorden. Cuando todo está en su sitio, la actividad concluye. Zonas del almacén: Zona izquierda: - Frigorífico (con tres estantes internos) - Congelador (con tres estantes internos). Zona central: Estantería principal de 4 baldas (de madera): - Balda superior: productos secos. - Balda media-alta: conservas. - Balda media-baja: fruta. - Balda inferior: verduras y tubérculos. Zona derecha: Con una separación de la estantería central: - Estantería metálica, con tres baldas a la izquierda. - Hueco a la derecha con una balda superior. - Encimera de trabajo. Escenario ordenado (como debe terminar): Zona izquierda: - Frigorífico: 1. Estante superior: dos quesos y docenas de huevos. 2. Estante central: botellas de leche. 3. Estante inferior: jamón cocido, fuet. - Congelador: 1. Estante superior: bolsas de verdura congelada. 2. Estante central: tarrinas de helado. 3. Estante inferior: cajón con pescado congelado y tuppers de pollo congelado. Zona central: Estantería principal de 4 baldas (de madera): - Balda superior: varios sacos de arroz, un par de cajas de cereales, un paquete de pasta, un recipiente con harina (cerrado con su tapa) y un bote de legumbres (cerrado con su tapa). - Balda media-alta: latas de diferentes conservas bien ordenadas. - Balda media-baja: cesto de manzanas, cesto de plátanos, cesta de naranjas y cesta de limones - Balda inferior: verduras frescas (cajón de lechuga y zanahorias), caja de tomates y tubérculos (saco de patatas, cajón de cebollas). Zona derecha: Con una separación de la estantería central: - Estantería metálica, con tres baldas a la izquierda para guantes, desinfectante y detergente. - Hueco a la derecha para el cubo de la fregona y balda superior para bayetas. - Encimera de trabajo con una fiambrera suelta, sin tapa. Escenario desordenado (cómo lo ve el alumnado al empezar): Zona izquierda: - Frigorífico: los productos de su interior están desordenados. Faltan el queso, los huevos y el fuet, que están fuera. - Congelador: los productos de su interior están desordenados. Zona central: - Balda superior: hay un paquete de pasta mal colocado, un bote de legumbres sin tapa, una cesta de limones que no debería estar ahí y una manzana suelta en el borde. También hay un queso (que debería estar en el frigorífico). - Balda media-alta: hay una lechuga suelta, un fuet (que debería estar en el frigorífico) y una caja de cereales (no es su lugar). - Balda media-baja: hay naranjas mezcladas con cebollas y una tapadera suelta (la del bote de legumbres). - Balda inferior: hay patatas fuera del saco, zanahorias sueltas sobre la caja tomates y una lata de conservas. También está la tapadera de la fiambrera (que debería estar en la encimera). - En el suelo: el cesto de plátanos directamente en el suelo, el saco de patatas, un saco de arroz, una lata de conservas, una caja de cereales y dos tomates rodando. Zona derecha: La zona de productos químicos está vacía o incompleta: el detergente está en la estantería de alimentos, el desinfectante junto a las conservas, los guantes sobre una caja de alimentos y las bayetas sobre el cesto de las manzanas. La fregona y el cubo están en medio de la zona de alimentos. En la encimera hay una fiambrera abierta, plátanos sueltos y algunos huevos (que deberían estar en el frigorífico) Acciones reorganizadas por zonas (para que el equipo lo tenga claro): Zona izquierda: - Queso (en estantería de productos secos) → estante del frigorífico. - Huevos (en la encimera) → estante de huevos del frigorífico. - Fuet (en estantería de conservas) → estante de fiambres del frigorífico. - Frigorífico desordenado→ reorganizar. - Congelador desordenado→ reorganizar. Zona central: Balda superior (productos secos): - Saco de arroz (en el suelo) → balda superior. - Caja de cereales (en balda media-alta) → balda superior. - Paquete de pasta (en balda superior mal colocado) → balda superior bien colocado. - Recipiente de harina abierto (en balda superior) → cerrar con su tapadera (que está en el suelo). - Bote de legumbres sin tapa (en balda superior) → cerrar con su tapa (que está en la balda media-baja). Balda media-alta (conservas): - Lata de conservas (en el suelo) → balda media-alta. - Lata de conservas (en la balda inferior) → balda media-alta. Balda media-baja (fruta): - Manzana suelta (en balda superior) → cesta de manzanas (balda media-baja). - Plátanos sueltos (en la encimera) → cesto de plátanos (balda media-baja). - Naranjas (mezcladas con cebollas en balda media-baja) → cesta de naranjas (balda media-baja). - Limones (en balda superior) → cesta de limones (balda media-baja). - Cesto de plátanos (en el suelo) → balda media-baja. Balda inferior (verduras y tubérculos): - Lechuga (en balda media-alta) → cajón de verduras frescas (balda inferior). - Tomates (en el suelo) → caja de tomates (balda inferior). - Zanahorias (sobre la caja de tomates) → cajón de verduras frescas (balda inferior). - Patatas (fuera del saco en balda inferior) → saco de patatas (balda inferior). - Saco de patatas (en el suelo) → balda inferior. - Cebollas (mezcladas con naranjas en balda media-baja) → cajón de cebollas (balda inferior). Zona derecha: - Detergente (en la balda inferior) → zona de productos químicos. - Desinfectante (junto a las conservas) → zona de productos químicos. - Guantes de limpieza (sobre una lata de conservas) → zona de productos químicos. - Fregona y cubo limpios y vacíos (en el suelo, tirados) → zona de limpieza. - Bayetas limpias (sobre el cesto de las manzanas) → zona de limpieza. Encimera: Fiambrera abierta (en la encimera) → cerrar con su tapadera (que está en la balda inferior). | F31: Mecánica de arrastre (sin feedback durante la actividad): - Si el alumnado arrastra un objeto a un lugar incorrecto el objeto regresa automáticamente a su posición inicial. No aparece ningún mensaje de error ni de explicación: el propio retorno del objeto indica que esa no es su ubicación. - Si el alumnado arrastra un objeto a su lugar correcto: el objeto se queda fijado en esa posición y ya no se puede volver a mover. El aprendizaje se produce por ensayo y error: el alumnado deduce las ubicaciones correctas por la lógica del almacén y por el retorno de los objetos mal colocados. Mensaje final (cuando todos los objetos están en su sitio): "¡Almacén organizado! Has colocado cada producto en su lugar, has protegido los alimentos, has separado los productos químicos y has dejado el almacén en condiciones seguras. Una buena organización ayuda a proteger los alimentos y a prevenir contaminaciones." Botón de pista / ayuda: Icono de bombilla o interrogación en una esquina de la pantalla. Al pulsarlo, aparece un mensaje orientativo que no revela la solución, sino que invita a seguir explorando: "Aún no has terminado de ordenar todo. Fíjate bien en las baldas de la estantería, en los productos que deberían estar en el frigorífico o en el congelador, en los recipientes que están abiertos y en las cosas que han quedado en el suelo. Revisa también la zona de productos de limpieza. ¡Sigue explorando!" (El botón puede pulsarse tantas veces como el alumnado quiera; el mensaje es siempre el mismo y no indica objetos concretos, solo zonas donde fijarse). **(Idea extra: Podría aparecer un mensaje diferente de ayuda para cada zona (un mensaje de nevera, otro de congelador, otro de estantería central...) cuando le queden pocos objetos)** | G31: ='Cont-Obj'!E:E -> 4.6 Almacenamiento seguro y organización de cámaras
A32: ='Cont-Obj'!A:A | B32: ='Cont-Obj'!B:B -> O4.8 Diferenciar entre fecha de caducidad y fecha de consumo preferente. | C32: ='Cont-Obj'!C:C -> 26 | E32: Leer texto | F32: El alumno se encuentra en el almacén del restaurante. En la pared hay un cartel informativo. El encargado le indica que lo lea antes de empezar a organizar los productos. Qué dice el encargado Le comunica que, antes de preparar la mercancía para el servicio, debe conocer las normas de almacenamiento y control de fechas. Para ello, le indica que consulte el cartel de la pared. Qué contiene el cartel El cartel explica los contenidos del temario 4.7 de forma breve y visual: - Sistema FIFO: los productos que llevan más tiempo almacenados se colocan delante para utilizarlos primero; los recién recibidos se colocan detrás. - Control de fechas: no basta con seguir el orden de llegada. También hay que revisar las etiquetas, porque un producto recibido más recientemente puede caducar antes. - Fecha de caducidad: una vez superada, el alimento no debe consumirse. - Fecha de consumo preferente: indica hasta cuándo el alimento mantiene sus propiedades de calidad. Superarla no significa automáticamente que sea inseguro, pero deben considerarse su conservación y las comprobaciones pertinentes. - Antes de utilizar un producto: comprobar la fecha y asegurarse de que el envase está en buen estado. Interacción El alumno pulsa el cartel para leerlo. Cuando termina, continúa hacia la actividad práctica. Esta pantalla tiene una función exclusivamente formativa: presentar la información que necesitará aplicar después. | G32: ='Cont-Obj'!E:E
A33: ='Cont-Obj'!A:A -> Módulo 4. Conservación y control de temperaturas | B33: ='Cont-Obj'!B:B -> O4.8 Aplicar sistemas adecuados de rotación de productos y control de fechas. | C33: ='Cont-Obj'!C:C -> 27 | E33: Título de la actividad: Fechas en orden: rota, compara y descarta. Enunciado: El restaurante necesita que organices los productos almacenados para preparar la mercancía que se utilizará durante el servicio. El almacén está ordenado, pero cuatro estantes esconden productos que no están bien colocados. Pulsa sobre ellos para revisarlos: en cada uno encontrarás productos del mismo tipo con diferentes fechas y deberás organizarlos de izquierda a derecha siguiendo el criterio correspondiente. Examina las etiquetas y compara las fechas. Si identificas un alimento cuya fecha de caducidad ya ha pasado, arrástralo a la papelera. Cuando termines, pulsa OK para comprobar tu decisión. Si algo no está bien, revisa y vuelve a intentarlo. ¡Demuestra que controlas las fechas! Descripción: Actividad interactiva de exploración y organización en el mismo almacén ordenado de la actividad anterior. El alumnado explora libremente el almacén. Solo cuatro puntos concretos (hidden objects) se resaltan al pasar el cursor por encima: - Paquetes de arroz de la balda superior de la estantería central. - Paquetes de jamón cocido del tercer estante del frigorífico. - Botellas de leche del segundo estante del frigorífico. - Latas de conserva de la balda media-alta de la estantería central. Al pulsar cada uno de ellos, la cámara hace zoom y aparecen los productos en primer plano, flotando, con sus etiquetas visibles. El alumnado debe arrastrarlos para ordenarlos de izquierda a derecha y usar la papelera cuando corresponda descartar un producto. Al terminar, pulsa OK para comprobar. El orden: en la parte superior de la pantalla hay una flecha horizontal que indica la dirección de ordenación (→) y un texto breve: "Coloca los productos de izquierda a derecha: el primero que debe utilizarse, a la izquierda; el último, a la derecha". Los productos se pueden arrastrar libremente y el sistema comprueba la posición final. Etiquetas: Cada producto lleva una etiqueta visible en primer plano con los siguientes datos: - Nombre del producto (arroz, jamón cocido, leche, conservas). - Fecha de recepción (para la Situación 1): "Recibido: hace X días". - Fecha de caducidad (para las Situaciones 2 y 3): "Caduca: dentro de X días" o "Caducó: hace X días". - Fecha de consumo preferente (para la Situación 4): "Consumo preferente: dentro de X días" o "Consumo preferente superado: hace X días". Las etiquetas son grandes, legibles y permanecen visibles mientras el alumnado manipula los productos. Los datos relevantes están destacados en negrita o con un color diferente para facilitar la comparación. Situaciones: Situación 1 — "El primero que llegó, el primero que sale" (Aplicar FIFO) Producto: paquetes de arroz (balda superior de la estantería central). Qué aparece en pantalla: tres paquetes de arroz con sus etiquetas de recepción: - Producto A: recibido hace 8 días. - Producto B: recibido hace 5 días. - Producto C: recibido ayer. Los productos aparecen en orden incorrecto. La papelera está visible, pero no debe usarse. Qué debe hacer el alumnado: ordenar de izquierda a derecha colocando primero el que lleva más tiempo almacenado y al final el más reciente. Solución correcta: A → B → C. No se descarta ninguno. Situación 2 — "No siempre sale antes el que llegó antes" (Comprobar las fechas antes de decidir) Producto: paquetes de jamón cocido (tercer estante del frigorífico, fiambres). Qué aparece en pantalla: tres paquetes de jamón cocido con etiquetas de recepción y caducidad: - Producto A: recibido hace 8 días. Caduca dentro de 10 días. - Producto B: recibido hace 5 días. Caduca dentro de 2 días. - Producto C: recibido ayer. Caduca dentro de 20 días. Los productos aparecen en orden incorrecto. La papelera está visible, pero no debe usarse. Qué debe hacer el alumnado: comparar las fechas de caducidad y ordenar de izquierda a derecha dando prioridad al que caduca antes, aunque no sea el que llegó primero. Solución correcta: B → A → C. No se descarta ninguno. Situación 3 — "Cuando la fecha ya pasó" (Fecha de caducidad superada) Producto: botellas de leche (segundo estante del frigorífico, lácteos). Qué aparece en pantalla: tres botellas de leche con etiquetas de caducidad: - Producto A: caduca dentro de 5 días. - Producto B: caducó hace 2 días. - Producto C: caduca dentro de 10 días. Los productos aparecen en orden incorrecto. La papelera está visible. Qué debe hacer el alumnado: identificar el producto caducado, arrastrarlo a la papelera y ordenar los dos restantes de izquierda a derecha según su fecha de caducidad. Solución correcta: arrastrar B a la papelera; ordenar A → C. Situación 4 — "No es lo mismo caducar que perder calidad" (Fecha de consumo preferente superada) Producto: latas de conserva (balda media-alta de la estantería central). Qué aparece en pantalla: tres latas de conserva con etiquetas de consumo preferente: - Producto A: consumo preferente dentro de 10 días. - Producto B: consumo preferente superado hace 3 días. - Producto C: consumo preferente dentro de 20 días. Los productos aparecen en orden incorrecto. La papelera está visible. Qué debe hacer el alumnado: ordenar de izquierda a derecha según la fecha de consumo preferente, colocando primero el que tiene la fecha más próxima. No debe descartar el producto B solo por haber superado su fecha de consumo preferente: debe distinguir entre caducidad y consumo preferente. Solución correcta: B → A → C. No se utiliza la papelera. | F33: Situación 1 – Aplicar FIFO: - Correcto: «Correcto. Has comprobado cuándo se recibió cada producto y has colocado primero el que lleva más tiempo almacenado». - Incorrecto: «Revisa las fechas de recepción. Según el sistema FIFO, el que lleva más tiempo almacenado debe quedar primero. En esta situación, los tres productos deben mantenerse disponibles: no uses la papelera». Situación 2 – Comprobar las fechas antes de decidir: - Correcto: «Correcto. Has comparado las fechas de caducidad y has dado prioridad al producto que caduca antes, aunque se recibiera después». - Incorrecto: «No te fijes solo en cuándo llegó cada producto. Compara sus fechas de caducidad y coloca primero el que caduca antes. En esta situación, los tres productos deben mantenerse disponibles: no uses la papelera». Situación 3 – Fecha de caducidad superada: - Correcto: «Correcto. Has descartado el producto cuya fecha de caducidad ha pasado y has ordenado los productos restantes según sus fechas». - Incorrecto: «Revisa las fechas de caducidad. El producto cuya fecha ya ha pasado no debe utilizarse: arrástralo a la papelera. Después, ordena los productos restantes colocando primero el que caduca antes». Situación 4 – Fecha de consumo preferente superada: - Correcto: «Correcto. Has ordenado los productos según sus fechas de consumo preferente y has distinguido esta fecha de la de caducidad, sin descartar automáticamente el producto que ha superado la suya». - Incorrecto: «Revisa las fechas de consumo preferente y ordena los productos colocando primero el que tiene la fecha más próxima. Recuerda que superar la fecha de consumo preferente no equivale a superar la de caducidad: no debes descartar automáticamente un producto solo por ese motivo». | G33: ='Cont-Obj'!E:E -> 4.7 Rotación y control de fechas
A34: ='Cont-Obj'!A:A -> Módulo 5. Limpieza, desinfección y mantenimiento | B34: ='Cont-Obj'!B:B -> O5.1 Conocer la importancia de la limpieza y la desinfección para prevenir riesgos alimentarios. | C34: ='Cont-Obj'!C:C -> 28 | E34: Texto | G34: ='Cont-Obj'!E:E -> 5.1 Limpieza y desinfección: una parte esencial de la seguridad alimentaria
A35: ='Cont-Obj'!A:A -> Módulo 5. Limpieza, desinfección y mantenimiento | B35: ='Cont-Obj'!B:B -> O5.2 Diferenciar entre limpiar y desinfectar | C35: ='Cont-Obj'!C:C -> 29 | E35: Cocina: pantalla principal. Pulsar sobre los diferentes objetos para que aparezcan en primer plano. Aparecerán en la parte izquierda de la pantalla y a su derecha, un caso (lo que ocurre con ese objeto: el cocinero ha terido que marcharse antes de tiempo y le ha pasado un trapo a la tabla de cortar) Pregunta ¿qué falta por hacer? | F35: Si seleccionas correctamente un elemento que necesita limpieza: ¡Correcto! Este utensilio, superficie o equipo debe limpiarse antes de volver a utilizarse. Mantenerlos limpios durante la jornada ayuda a prevenir la contaminación de los alimentos. Si intentas utilizar un utensilio sucio: No es correcto. Los utensilios y superficies que entran en contacto con los alimentos deben mantenerse limpios, especialmente cuando cambias de alimento o de tarea. Si utilizas directamente un utensilio empleado con alimentos crudos: No es correcto. Debes evitar utilizar el mismo material sin aplicar antes las medidas necesarias de limpieza y desinfección. De lo contrario, podrías favorecer una contaminación cruzada. Si colocas un utensilio limpio sobre una superficie sucia: No es correcto. Un utensilio limpio puede contaminarse al entrar en contacto con una superficie sucia. Los utensilios limpios deben mantenerse en zonas protegidas y libres de contaminación. Si limpias correctamente un equipo siguiendo el procedimiento: ¡Correcto! Los equipos deben limpiarse siguiendo las instrucciones del fabricante y los procedimientos establecidos por el establecimiento. Si intentas limpiar un equipo mientras está funcionando: No es correcto. Los equipos deben limpiarse de forma segura y nunca mientras están en funcionamiento. Si utilizas un utensilio deteriorado: No es correcto. Las grietas, roturas y zonas desgastadas pueden acumular restos de alimentos y microorganismos. Debes retirarlo o comunicar la incidencia a la persona responsable. Si completas correctamente toda la revisión: ¡Zona preparada! Has comprobado los utensilios, superficies y equipos y has aplicado las medidas necesarias antes de continuar con la manipulación de alimentos. | G35: ='Cont-Obj'!E:E -> 5.2 ¿Limpiar o desinfectar?
A36: ='Cont-Obj'!A:A -> Módulo 5. Limpieza, desinfección y mantenimiento | B36: ='Cont-Obj'!B:B -> O5.3 Comprender el orden adecuado en el que debe realizarse la limpieza y la desinfección | C36: ='Cont-Obj'!C:C -> 29 | E36: Cocina: pantalla principal. Pulsar sobre los diferentes objetos para que aparezcan en primer plano. Aparecerán en la parte izquierda de la pantalla y a su derecha, un caso (lo que ocurre con ese objeto: el cocinero ha terido que marcharse antes de tiempo y le ha pasado un trapo a la tabla de cortar) Pregunta ¿qué falta por hacer? | F36: Si seleccionas correctamente un elemento que necesita limpieza: ¡Correcto! Este utensilio, superficie o equipo debe limpiarse antes de volver a utilizarse. Mantenerlos limpios durante la jornada ayuda a prevenir la contaminación de los alimentos. Si intentas utilizar un utensilio sucio: No es correcto. Los utensilios y superficies que entran en contacto con los alimentos deben mantenerse limpios, especialmente cuando cambias de alimento o de tarea. Si utilizas directamente un utensilio empleado con alimentos crudos: No es correcto. Debes evitar utilizar el mismo material sin aplicar antes las medidas necesarias de limpieza y desinfección. De lo contrario, podrías favorecer una contaminación cruzada. Si colocas un utensilio limpio sobre una superficie sucia: No es correcto. Un utensilio limpio puede contaminarse al entrar en contacto con una superficie sucia. Los utensilios limpios deben mantenerse en zonas protegidas y libres de contaminación. Si limpias correctamente un equipo siguiendo el procedimiento: ¡Correcto! Los equipos deben limpiarse siguiendo las instrucciones del fabricante y los procedimientos establecidos por el establecimiento. Si intentas limpiar un equipo mientras está funcionando: No es correcto. Los equipos deben limpiarse de forma segura y nunca mientras están en funcionamiento. Si utilizas un utensilio deteriorado: No es correcto. Las grietas, roturas y zonas desgastadas pueden acumular restos de alimentos y microorganismos. Debes retirarlo o comunicar la incidencia a la persona responsable. Si completas correctamente toda la revisión: ¡Zona preparada! Has comprobado los utensilios, superficies y equipos y has aplicado las medidas necesarias antes de continuar con la manipulación de alimentos. | G36: ='Cont-Obj'!E:E -> 5.2 ¿Limpiar o desinfectar?
A37: ='Cont-Obj'!A:A -> Módulo 5. Limpieza, desinfección y mantenimiento | B37: ='Cont-Obj'!B:B -> O5.4 Aplicar correctamente las normas de seguridad durante el uso y almacenamiento de productos químicos. | C37: ='Cont-Obj'!C:C -> 29 | E37: Cocina: pantalla principal. Pulsar sobre los diferentes objetos para que aparezcan en primer plano. Aparecerán en la parte izquierda de la pantalla y a su derecha, un caso (lo que ocurre con ese objeto: el cocinero ha terido que marcharse antes de tiempo y le ha pasado un trapo a la tabla de cortar) Pregunta ¿qué falta por hacer? | F37: Si seleccionas correctamente un elemento que necesita limpieza: ¡Correcto! Este utensilio, superficie o equipo debe limpiarse antes de volver a utilizarse. Mantenerlos limpios durante la jornada ayuda a prevenir la contaminación de los alimentos. Si intentas utilizar un utensilio sucio: No es correcto. Los utensilios y superficies que entran en contacto con los alimentos deben mantenerse limpios, especialmente cuando cambias de alimento o de tarea. Si utilizas directamente un utensilio empleado con alimentos crudos: No es correcto. Debes evitar utilizar el mismo material sin aplicar antes las medidas necesarias de limpieza y desinfección. De lo contrario, podrías favorecer una contaminación cruzada. Si colocas un utensilio limpio sobre una superficie sucia: No es correcto. Un utensilio limpio puede contaminarse al entrar en contacto con una superficie sucia. Los utensilios limpios deben mantenerse en zonas protegidas y libres de contaminación. Si limpias correctamente un equipo siguiendo el procedimiento: ¡Correcto! Los equipos deben limpiarse siguiendo las instrucciones del fabricante y los procedimientos establecidos por el establecimiento. Si intentas limpiar un equipo mientras está funcionando: No es correcto. Los equipos deben limpiarse de forma segura y nunca mientras están en funcionamiento. Si utilizas un utensilio deteriorado: No es correcto. Las grietas, roturas y zonas desgastadas pueden acumular restos de alimentos y microorganismos. Debes retirarlo o comunicar la incidencia a la persona responsable. Si completas correctamente toda la revisión: ¡Zona preparada! Has comprobado los utensilios, superficies y equipos y has aplicado las medidas necesarias antes de continuar con la manipulación de alimentos. | G37: ='Cont-Obj'!E:E -> 5.3 Productos de limpieza y desinfección
A38: ='Cont-Obj'!A:A -> Módulo 5. Limpieza, desinfección y mantenimiento | B38: ='Cont-Obj'!B:B -> O5.5 Seleccionar los productos de limpieza y desinfección adecuados siguiendo las instrucciones y procedimientos establecidos. | C38: ='Cont-Obj'!C:C -> 29 | E38: Cocina: pantalla principal. Pulsar sobre los diferentes objetos para que aparezcan en primer plano. Aparecerán en la parte izquierda de la pantalla y a su derecha, un caso (lo que ocurre con ese objeto: el cocinero ha terido que marcharse antes de tiempo y le ha pasado un trapo a la tabla de cortar) Pregunta ¿qué falta por hacer? | F38: Si seleccionas correctamente un elemento que necesita limpieza: ¡Correcto! Este utensilio, superficie o equipo debe limpiarse antes de volver a utilizarse. Mantenerlos limpios durante la jornada ayuda a prevenir la contaminación de los alimentos. Si intentas utilizar un utensilio sucio: No es correcto. Los utensilios y superficies que entran en contacto con los alimentos deben mantenerse limpios, especialmente cuando cambias de alimento o de tarea. Si utilizas directamente un utensilio empleado con alimentos crudos: No es correcto. Debes evitar utilizar el mismo material sin aplicar antes las medidas necesarias de limpieza y desinfección. De lo contrario, podrías favorecer una contaminación cruzada. Si colocas un utensilio limpio sobre una superficie sucia: No es correcto. Un utensilio limpio puede contaminarse al entrar en contacto con una superficie sucia. Los utensilios limpios deben mantenerse en zonas protegidas y libres de contaminación. Si limpias correctamente un equipo siguiendo el procedimiento: ¡Correcto! Los equipos deben limpiarse siguiendo las instrucciones del fabricante y los procedimientos establecidos por el establecimiento. Si intentas limpiar un equipo mientras está funcionando: No es correcto. Los equipos deben limpiarse de forma segura y nunca mientras están en funcionamiento. Si utilizas un utensilio deteriorado: No es correcto. Las grietas, roturas y zonas desgastadas pueden acumular restos de alimentos y microorganismos. Debes retirarlo o comunicar la incidencia a la persona responsable. Si completas correctamente toda la revisión: ¡Zona preparada! Has comprobado los utensilios, superficies y equipos y has aplicado las medidas necesarias antes de continuar con la manipulación de alimentos. | G38: ='Cont-Obj'!E:E -> 5.3 Productos de limpieza y desinfección
A39: ='Cont-Obj'!A:A -> Módulo 5. Limpieza, desinfección y mantenimiento | B39: ='Cont-Obj'!B:B -> O5.6 Gestionar los residuos de forma que se reduzcan los riesgos de contaminación y aparición de plagas. | C39: ='Cont-Obj'!C:C -> 30 | E39: Leer texto | F39: Introducción teórica: la gestión de residuos en la cocina Antes de comenzar la actividad práctica, el encargado explicará al alumno cómo deben gestionarse los residuos en una cocina profesional. Texto del encargado: «Durante una jornada de trabajo, los residuos se acumulan continuamente. Gestionarlos correctamente es fundamental para mantener la cocina limpia y evitar que puedan contaminar los alimentos o las superficies donde los preparamos. - Cada residuo en su lugar: En la cocina generamos distintos tipos de residuos, como restos de alimentos, envases y materiales desechables. Debemos depositarlos en los recipientes habilitados para cada tipo. - Contenedores en buenas condiciones: No debemos esperar a que un contenedor esté completamente lleno para retirarlo. Si está demasiado lleno, dificulta el trabajo y puede favorecer que los residuos se derramen o entren en contacto con otras superficies. Los recipientes deben mantenerse limpios y, siempre que sea posible, disponer de tapa. También debemos retirar los residuos con la frecuencia necesaria para evitar que se acumulen en la zona de trabajo. - Residuos alejados de los alimentos: Los restos de comida y los envases usados no deben permanecer junto a los alimentos ni sobre las superficies donde los preparamos. Mantén la zona de trabajo despejada y retira los residuos cuando sea necesario. - Higiene después de manipular residuos: Cuando manipules basura, debes lavarte las manos antes de volver a trabajar con alimentos. Así evitas transferir suciedad y posibles contaminantes a los alimentos o a los utensilios. - Recuerda: mantener la cocina limpia no consiste únicamente en tirar la basura. También debes observar lo que ocurre a tu alrededor y actuar antes de que los residuos se conviertan en un problema». Una vez finalizada la explicación, cambiará la pantalla y aparecerá el enunciado de la actividad. El alumno comenzará entonces su jornada de trabajo. | G39: ='Cont-Obj'!E:E -> 5.4 Gestión de residuos
A40: ='Cont-Obj'!A:A -> Módulo 5. Limpieza, desinfección y mantenimiento | B40: ='Cont-Obj'!B:B -> O5.7 Identificar señales de presencia de plagas | C40: ='Cont-Obj'!C:C -> 31 | E40: Título de la actividad: Una cocina limpia, un trabajo seguro Enunciado de la actividad: Durante la jornada de trabajo, se generan residuos continuamente. Tu tarea es mantener la zona de trabajo limpia y gestionar correctamente la basura para evitar que interfiera con la preparación de alimentos. A medida que avances, encontrarás distintas situaciones que tendrás que resolver. Observa el estado de los contenedores, identifica los residuos y decide qué debes hacer antes de continuar trabajando. Cuando consideres que has terminado de resolver una situación, pulsa el icono del timbre para comprobar si has actuado correctamente. Descripción de la actividad: 2. Descripción general de la pantalla y la interacción La actividad se desarrollará en una zona de trabajo de la cocina que irá cambiando de estado a medida que avance la jornada. El alumno tendrá que resolver siete situaciones relacionadas con la gestión de residuos. No es necesario crear siete escenarios completamente diferentes. La propuesta es utilizar una escena principal con los contenedores, la superficie de trabajo y los elementos necesarios, modificando su estado o incorporando nuevos elementos en cada situación. Elementos visuales de la escena - Zona de preparación: una superficie donde aparecen alimentos y utensilios, y en la que se generan residuos durante las tareas. - Contenedores de residuos: recipientes identificados para los distintos tipos de residuos. Su capacidad y estado podrán variar durante la actividad. - Residuos interactivos: restos de alimentos, envases y materiales desechables que el alumno deberá recoger y depositar correctamente. - Zona destinada a retirar los residuos: espacio que permita representar el traslado de un contenedor o de los residuos al lugar correspondiente. - Elementos de higiene: un fregadero con jabón para que el alumno pueda lavarse las manos después de manipular residuos. - Icono del timbre: situado fuera de la escena, permitirá solicitar la revisión de las acciones realizadas. Los objetos interactivos se resaltarán al pasar el cursor por encima. El alumno podrá recoger residuos, arrastrarlos hasta un contenedor, abrir o cerrar una tapa, retirar un recipiente, desplazarse hasta el fregadero e interactuar con los elementos disponibles. La actividad no presentará preguntas de opción múltiple. El alumno tendrá que demostrar lo que sabe mediante acciones directas sobre los objetos. Situación 1: Cada residuo en su lugar Contexto: Al comenzar la jornada, el alumno encuentra varios residuos generados durante la preparación de alimentos. Los contenedores están disponibles y todavía se encuentran en condiciones adecuadas para su uso. En la parte superior de la pantalla aparecerá el siguiente texto: «Vamos a empezar con la preparación. Aquí tienes los contenedores destinados a los distintos residuos. A medida que trabajes, tendrás que mantener la zona despejada. Encárgate de estos residuos antes de continuar». Dinámica detallada: 1. El alumno observa los residuos que hay en la zona de trabajo. 2. Identifica los restos de alimentos, los envases y los materiales desechables. 3. Selecciona cada residuo y lo arrastra hasta el contenedor correspondiente. 4. Si deposita un residuo en un recipiente inadecuado, podrá volver a recogerlo y corregir su decisión. 5. Cuando considere que ha terminado, pulsa el timbre para solicitar la revisión. Resolución esperada: Cada residuo debe depositarse en el contenedor habilitado para ese tipo de residuo. La finalidad es que el alumno identifique los residuos y los gestione correctamente sin dejar restos sobre la superficie de trabajo. Situación 2: El contenedor se está llenando Contexto: Durante la preparación, uno de los contenedores ha acumulado una cantidad importante de residuos. Todavía queda espacio, pero el recipiente empieza a resultar incómodo para seguir trabajando. En la parte superior aparecerá el siguiente texto: «La preparación continúa y este contenedor está cada vez más lleno. Todavía cabe algo más, pero debes decidir si puedes seguir utilizándolo o si ha llegado el momento de retirarlo». Dinámica detallada: 1. El alumno observa el estado del contenedor y la cantidad de residuos que contiene. 2. Puede seguir depositando residuos en él o decidir retirarlo. 3. Si continúa utilizándolo hasta que los residuos sobresalen o se derraman, la escena mostrará las consecuencias de esa decisión. 4. Si decide retirarlo, deberá trasladarlo al lugar correspondiente y dejar disponible un recipiente adecuado para continuar trabajando. 5. Cuando considere que ha terminado, pulsa el timbre. Resolución esperada: El alumno debe retirar el contenedor cuando sea necesario, sin esperar a que se llene por completo. La decisión debe basarse en su estado y en la necesidad de evitar derrames, dificultades de manejo o interferencias con la zona de trabajo. Situación 3: Residuos junto a los alimentos Contexto: Después de preparar varios ingredientes, han quedado restos de alimentos y envases junto a una superficie donde se están preparando nuevos alimentos. En la parte superior aparecerá el siguiente texto: «Tenemos que continuar con la preparación, pero han quedado residuos cerca de la zona donde estamos trabajando. Antes de seguir, revisa qué debes hacer». Dinámica detallada: 1. El alumno observa la superficie de trabajo y detecta los restos de alimentos y envases. 2. Debe decidir si puede dejarlos donde están o si debe retirarlos antes de continuar. 3. Si decide seguir trabajando sin retirarlos, la actividad mostrará que los residuos permanecen junto a los alimentos y ocupan parte de la zona de preparación. 4. Si actúa correctamente, recogerá los residuos y los depositará en los contenedores correspondientes. 5. Cuando la zona quede despejada, pulsará el timbre. Resolución esperada: El alumno debe retirar los residuos y mantenerlos alejados de los alimentos y de las superficies de trabajo. No basta con desplazarlos a otra parte de la misma superficie si siguen interfiriendo con la preparación. Situación 4: Un contenedor sin tapa Contexto Al continuar la jornada, el alumno observa que uno de los contenedores permanece abierto. En la parte superior aparecerá el siguiente texto: «Antes de continuar, echa un vistazo a los contenedores de la zona. Comprueba si todos están en condiciones adecuadas para seguir utilizándolos». Dinámica detallada: 1. El alumno inspecciona los contenedores disponibles. 2. Identifica el recipiente que permanece abierto. 3. Debe decidir si lo deja así o si coloca la tapa. 4. Si cierra el contenedor correctamente, podrá continuar con la actividad. 5. Si considera que el contenedor puede permanecer abierto sin revisar su estado, el feedback le ayudará a reconocer la importancia de mantenerlo adecuadamente. Resolución esperada El alumno debe mantener los contenedores limpios y, siempre que sea posible, con tapa. La tapa ayuda a contener los residuos y a reducir su exposición al entorno. La actividad no debe transmitir que cualquier recipiente sin tapa sea automáticamente inadecuado en todas las circunstancias, sino reforzar que debe mantenerse cerrado cuando corresponda. Situación 5: Manipular la basura y volver al trabajo Contexto: Uno de los contenedores necesita retirarse. El alumno lo lleva al lugar correspondiente y, al terminar, debe volver a la zona de preparación. En la parte superior aparecerá el siguiente texto: «Ya has retirado los residuos y puedes volver a la preparación. Antes de continuar trabajando con alimentos, revisa qué debes hacer». Dinámica detallada 1. El alumno recoge o manipula el contenedor y traslada los residuos al lugar correspondiente. 2. Regresa a la zona de preparación. 3. Antes de interactuar con los alimentos, aparece una indicación que le invita a decidir cómo continuar. 4. El alumno puede dirigirse directamente a los alimentos o acudir al fregadero. 5. Si elige lavarse las manos, deberá interactuar con el grifo y el jabón y completar la acción de lavado. 6. Cuando considere que está listo para continuar, pulsa el timbre. Resolución esperada Después de manipular residuos, el alumno debe lavarse las manos antes de volver a trabajar con alimentos. No basta con retirarse de la zona de basura ni con enjuagarse las manos sin utilizar jabón. El fregadero y el jabón permitirán representar esta acción de forma directa. Situación 6: Contenedor sucio Contexto Durante la jornada, el alumno detecta que uno de los contenedores presenta suciedad acumulada en su interior y exterior. En la parte superior aparecerá el siguiente texto: «Este contenedor se ha ensuciado durante el trabajo. ¿Puedes seguir utilizándolo en estas condiciones o debes hacer algo antes?». Dinámica detallada 1. El alumno inspecciona el recipiente y detecta la suciedad acumulada. 2. Debe decidir si continúa utilizándolo o si aplica las medidas necesarias para mantenerlo limpio. 3. Si decide seguir utilizándolo sin actuar, el contenedor permanecerá sucio y podrá acumular más residuos. 4. Si actúa correctamente, deberá gestionar el recipiente según el procedimiento establecido, utilizando los medios de limpieza disponibles en la actividad. 5. Una vez resuelta la incidencia, pulsa el timbre. Resolución esperada El alumno debe mantener los contenedores limpios y aplicar las medidas de limpieza establecidas por el establecimiento. La actividad no necesita desarrollar aquí una lección completa sobre limpieza y desinfección, ya que el objetivo se centra en reconocer la necesidad de mantener los recipientes de residuos en condiciones higiénicas. Situación 7: Residuos acumulados durante la jornada Contexto Al finalizar una tarea, el alumno observa que se han acumulado restos de alimentos y materiales desechables. El contenedor todavía dispone de espacio, pero la zona de trabajo empieza a estar desordenada. En la parte superior aparecerá el siguiente texto: «La jornada continúa y se han acumulado nuevos residuos. El contenedor todavía tiene espacio, pero debes decidir si conviene dejarlos ahí durante el resto del trabajo o retirarlos ahora». Dinámica detallada 1. El alumno observa el estado de la zona de trabajo y de los contenedores. 2. Debe valorar si los residuos pueden permanecer allí o si es necesario retirarlos. 3. Si decide dejarlos acumulados durante el resto de la jornada, la zona permanecerá desordenada y los residuos seguirán presentes cerca del área de preparación. 4. Si decide actuar, recogerá los residuos y los depositará en el contenedor correspondiente. 5. Si el contenedor está en condiciones de seguir utilizándose, podrá continuar con él. Si está demasiado lleno o sucio, deberá resolver también esa situación. 6. Cuando considere que ha terminado, pulsa el timbre. Resolución esperada El alumno debe retirar los residuos con la frecuencia necesaria para evitar su acumulación en la zona de trabajo. No debe esperar necesariamente a que el contenedor esté lleno: debe observar el estado de la cocina y actuar cuando los residuos puedan interferir con la higiene o con la preparación de alimentos. Cierre de la actividad Al superar las siete situaciones, aparecerá un mensaje final: «Buen trabajo. Durante la jornada has aprendido que gestionar los residuos no consiste únicamente en tirar la basura. También debes utilizar los contenedores adecuados, mantenerlos limpios y en buenas condiciones, retirar los residuos con la frecuencia necesaria y lavarte las manos después de manipularlos. Recuerda que una cocina limpia y organizada ayuda a prevenir contaminaciones y permite trabajar con mayor seguridad». Feedback El feedback aparecerá cuando el alumno pulse el icono del timbre para solicitar la revisión de sus acciones. Si ha cometido un error, recibirá una indicación para reflexionar sobre lo ocurrido y podrá volver a la escena para corregirlo. En el primer intento se priorizarán preguntas o pistas breves. Si el alumno repite el error, recibirá una explicación más explícita de la práctica adecuada y de sus consecuencias. | F40: El feedback Situación 1: Cada residuo en su lugar Si deposita un residuo en un contenedor incorrecto: Primer feedback: «Revisa el residuo que acabas de depositar. ¿Es este el contenedor habilitado para ese tipo de material?». Si necesita más ayuda: «Cada tipo de residuo debe depositarse en el recipiente correspondiente. Comprueba la identificación de los contenedores y coloca el residuo en el lugar adecuado». Si deposita todos los residuos correctamente: «Has identificado los distintos residuos y los has depositado en sus contenedores correspondientes. Así mantienes la zona de trabajo más ordenada y facilitas una gestión adecuada de la basura». Situación 2: El contenedor se está llenando Si continúa utilizando el contenedor hasta que los residuos sobresalen o se derraman: Primer feedback: «El contenedor está cada vez más lleno. ¿Es necesario esperar a que no quepa nada más para retirarlo?». Si necesita más ayuda: «Un contenedor demasiado lleno puede provocar derrames y dificultar su manejo. Retíralo cuando sea necesario y deja disponible un recipiente adecuado para continuar trabajando». Si retira el contenedor a tiempo: «Has detectado que el contenedor necesitaba retirarse antes de llenarse por completo. Anticiparte evita derrames y facilita el trabajo en la cocina». Situación 3: Residuos junto a los alimentos Si continúa trabajando sin retirar los residuos: Primer feedback: «Los residuos siguen junto a la zona de preparación. ¿Qué podría ocurrir si permanecen cerca de los alimentos y de las superficies de trabajo?». Si necesita más ayuda: «Los residuos pueden favorecer la contaminación de los alimentos o de las superficies donde se preparan. Retíralos y mantén despejada la zona antes de continuar». Si retira los residuos correctamente: «Has retirado los restos y los envases de la zona de preparación. Mantener los residuos alejados de los alimentos ayuda a reducir el riesgo de contaminación». Situación 4: Un contenedor sin tapa Si deja abierto el contenedor cuando debería estar cerrado: Primer feedback: «Has revisado el contenedor, pero sigue abierto. ¿Cómo puedes mantener los residuos más protegidos y contenidos?». Si necesita más ayuda: «Los contenedores deben mantenerse limpios y, siempre que sea posible, con tapa. Ciérralo cuando corresponda para evitar que los residuos queden expuestos innecesariamente». Si coloca la tapa correctamente: «Has comprobado el estado del contenedor y lo has dejado cerrado. Recuerda mantener los recipientes en condiciones higiénicas durante toda la jornada». Situación 5: Manipular la basura y volver al trabajo Si vuelve directamente a manipular alimentos sin lavarse las manos: Primer feedback: «Acabas de manipular residuos. ¿Puedes volver directamente a trabajar con alimentos sin realizar ninguna medida de higiene?». Si necesita más ayuda: «Al manipular basura, las manos pueden contaminarse. Debes lavártelas con agua y jabón antes de volver a trabajar con alimentos». Si se lava correctamente las manos: «Te has lavado las manos después de manipular residuos. Así reduces el riesgo de transferir suciedad y contaminantes a los alimentos y utensilios». Situación 6: Contenedor sucio Si sigue utilizando el contenedor sin actuar: Primer feedback: «El recipiente presenta suciedad acumulada. ¿Es adecuado mantenerlo en esas condiciones durante toda la jornada?». Si necesita más ayuda: «Los contenedores de residuos también deben mantenerse limpios. Aplica las medidas de limpieza establecidas para evitar que la suciedad se acumule». Si gestiona correctamente la limpieza del recipiente: «Has detectado la suciedad y has actuado para mantener el contenedor en condiciones higiénicas. Recuerda que la limpieza de los recipientes forma parte de la gestión correcta de los residuos». Situación 7: Residuos acumulados durante la jornada Si deja los residuos acumulados porque el contenedor todavía tiene espacio: Primer feedback: «El contenedor no está lleno, pero los residuos se han acumulado en la zona de trabajo. ¿Es necesario esperar a llenarlo para retirarlos?». Si necesita más ayuda: «Los residuos deben retirarse con la frecuencia necesaria para evitar que se acumulen e interfieran con la higiene de la cocina. Recógelos y deposítalos en el lugar correspondiente». Si retira los residuos y deja la zona despejada: «Has retirado los residuos sin esperar a que el contenedor estuviera lleno. Observar el estado de la zona y actuar a tiempo ayuda a mantener unas condiciones higiénicas durante toda la jornada». | G40: ='Cont-Obj'!E:E -> 5.5 Prevención y control de plagas
A41: ='Cont-Obj'!A:A -> Módulo 5. Limpieza, desinfección y mantenimiento | B41: ='Cont-Obj'!B:B -> O5.8 Conocer que las incidencias de presencia de plagas se debe comunicar siguiendo el procedimiento establecido. | C41: ='Cont-Obj'!C:C -> 31 | E41: Título de la actividad: Una cocina limpia, un trabajo seguro Enunciado de la actividad: Durante la jornada de trabajo, se generan residuos continuamente. Tu tarea es mantener la zona de trabajo limpia y gestionar correctamente la basura para evitar que interfiera con la preparación de alimentos. A medida que avances, encontrarás distintas situaciones que tendrás que resolver. Observa el estado de los contenedores, identifica los residuos y decide qué debes hacer antes de continuar trabajando. Cuando consideres que has terminado de resolver una situación, pulsa el icono del timbre para comprobar si has actuado correctamente. Descripción de la actividad: 2. Descripción general de la pantalla y la interacción La actividad se desarrollará en una zona de trabajo de la cocina que irá cambiando de estado a medida que avance la jornada. El alumno tendrá que resolver siete situaciones relacionadas con la gestión de residuos. No es necesario crear siete escenarios completamente diferentes. La propuesta es utilizar una escena principal con los contenedores, la superficie de trabajo y los elementos necesarios, modificando su estado o incorporando nuevos elementos en cada situación. Elementos visuales de la escena - Zona de preparación: una superficie donde aparecen alimentos y utensilios, y en la que se generan residuos durante las tareas. - Contenedores de residuos: recipientes identificados para los distintos tipos de residuos. Su capacidad y estado podrán variar durante la actividad. - Residuos interactivos: restos de alimentos, envases y materiales desechables que el alumno deberá recoger y depositar correctamente. - Zona destinada a retirar los residuos: espacio que permita representar el traslado de un contenedor o de los residuos al lugar correspondiente. - Elementos de higiene: un fregadero con jabón para que el alumno pueda lavarse las manos después de manipular residuos. - Icono del timbre: situado fuera de la escena, permitirá solicitar la revisión de las acciones realizadas. Los objetos interactivos se resaltarán al pasar el cursor por encima. El alumno podrá recoger residuos, arrastrarlos hasta un contenedor, abrir o cerrar una tapa, retirar un recipiente, desplazarse hasta el fregadero e interactuar con los elementos disponibles. La actividad no presentará preguntas de opción múltiple. El alumno tendrá que demostrar lo que sabe mediante acciones directas sobre los objetos. Situación 1: Cada residuo en su lugar Contexto: Al comenzar la jornada, el alumno encuentra varios residuos generados durante la preparación de alimentos. Los contenedores están disponibles y todavía se encuentran en condiciones adecuadas para su uso. En la parte superior de la pantalla aparecerá el siguiente texto: «Vamos a empezar con la preparación. Aquí tienes los contenedores destinados a los distintos residuos. A medida que trabajes, tendrás que mantener la zona despejada. Encárgate de estos residuos antes de continuar». Dinámica detallada: 1. El alumno observa los residuos que hay en la zona de trabajo. 2. Identifica los restos de alimentos, los envases y los materiales desechables. 3. Selecciona cada residuo y lo arrastra hasta el contenedor correspondiente. 4. Si deposita un residuo en un recipiente inadecuado, podrá volver a recogerlo y corregir su decisión. 5. Cuando considere que ha terminado, pulsa el timbre para solicitar la revisión. Resolución esperada: Cada residuo debe depositarse en el contenedor habilitado para ese tipo de residuo. La finalidad es que el alumno identifique los residuos y los gestione correctamente sin dejar restos sobre la superficie de trabajo. Situación 2: El contenedor se está llenando Contexto: Durante la preparación, uno de los contenedores ha acumulado una cantidad importante de residuos. Todavía queda espacio, pero el recipiente empieza a resultar incómodo para seguir trabajando. En la parte superior aparecerá el siguiente texto: «La preparación continúa y este contenedor está cada vez más lleno. Todavía cabe algo más, pero debes decidir si puedes seguir utilizándolo o si ha llegado el momento de retirarlo». Dinámica detallada: 1. El alumno observa el estado del contenedor y la cantidad de residuos que contiene. 2. Puede seguir depositando residuos en él o decidir retirarlo. 3. Si continúa utilizándolo hasta que los residuos sobresalen o se derraman, la escena mostrará las consecuencias de esa decisión. 4. Si decide retirarlo, deberá trasladarlo al lugar correspondiente y dejar disponible un recipiente adecuado para continuar trabajando. 5. Cuando considere que ha terminado, pulsa el timbre. Resolución esperada: El alumno debe retirar el contenedor cuando sea necesario, sin esperar a que se llene por completo. La decisión debe basarse en su estado y en la necesidad de evitar derrames, dificultades de manejo o interferencias con la zona de trabajo. Situación 3: Residuos junto a los alimentos Contexto: Después de preparar varios ingredientes, han quedado restos de alimentos y envases junto a una superficie donde se están preparando nuevos alimentos. En la parte superior aparecerá el siguiente texto: «Tenemos que continuar con la preparación, pero han quedado residuos cerca de la zona donde estamos trabajando. Antes de seguir, revisa qué debes hacer». Dinámica detallada: 1. El alumno observa la superficie de trabajo y detecta los restos de alimentos y envases. 2. Debe decidir si puede dejarlos donde están o si debe retirarlos antes de continuar. 3. Si decide seguir trabajando sin retirarlos, la actividad mostrará que los residuos permanecen junto a los alimentos y ocupan parte de la zona de preparación. 4. Si actúa correctamente, recogerá los residuos y los depositará en los contenedores correspondientes. 5. Cuando la zona quede despejada, pulsará el timbre. Resolución esperada: El alumno debe retirar los residuos y mantenerlos alejados de los alimentos y de las superficies de trabajo. No basta con desplazarlos a otra parte de la misma superficie si siguen interfiriendo con la preparación. Situación 4: Un contenedor sin tapa Contexto Al continuar la jornada, el alumno observa que uno de los contenedores permanece abierto. En la parte superior aparecerá el siguiente texto: «Antes de continuar, echa un vistazo a los contenedores de la zona. Comprueba si todos están en condiciones adecuadas para seguir utilizándolos». Dinámica detallada: 1. El alumno inspecciona los contenedores disponibles. 2. Identifica el recipiente que permanece abierto. 3. Debe decidir si lo deja así o si coloca la tapa. 4. Si cierra el contenedor correctamente, podrá continuar con la actividad. 5. Si considera que el contenedor puede permanecer abierto sin revisar su estado, el feedback le ayudará a reconocer la importancia de mantenerlo adecuadamente. Resolución esperada El alumno debe mantener los contenedores limpios y, siempre que sea posible, con tapa. La tapa ayuda a contener los residuos y a reducir su exposición al entorno. La actividad no debe transmitir que cualquier recipiente sin tapa sea automáticamente inadecuado en todas las circunstancias, sino reforzar que debe mantenerse cerrado cuando corresponda. Situación 5: Manipular la basura y volver al trabajo Contexto: Uno de los contenedores necesita retirarse. El alumno lo lleva al lugar correspondiente y, al terminar, debe volver a la zona de preparación. En la parte superior aparecerá el siguiente texto: «Ya has retirado los residuos y puedes volver a la preparación. Antes de continuar trabajando con alimentos, revisa qué debes hacer». Dinámica detallada 1. El alumno recoge o manipula el contenedor y traslada los residuos al lugar correspondiente. 2. Regresa a la zona de preparación. 3. Antes de interactuar con los alimentos, aparece una indicación que le invita a decidir cómo continuar. 4. El alumno puede dirigirse directamente a los alimentos o acudir al fregadero. 5. Si elige lavarse las manos, deberá interactuar con el grifo y el jabón y completar la acción de lavado. 6. Cuando considere que está listo para continuar, pulsa el timbre. Resolución esperada Después de manipular residuos, el alumno debe lavarse las manos antes de volver a trabajar con alimentos. No basta con retirarse de la zona de basura ni con enjuagarse las manos sin utilizar jabón. El fregadero y el jabón permitirán representar esta acción de forma directa. Situación 6: Contenedor sucio Contexto Durante la jornada, el alumno detecta que uno de los contenedores presenta suciedad acumulada en su interior y exterior. En la parte superior aparecerá el siguiente texto: «Este contenedor se ha ensuciado durante el trabajo. ¿Puedes seguir utilizándolo en estas condiciones o debes hacer algo antes?». Dinámica detallada 1. El alumno inspecciona el recipiente y detecta la suciedad acumulada. 2. Debe decidir si continúa utilizándolo o si aplica las medidas necesarias para mantenerlo limpio. 3. Si decide seguir utilizándolo sin actuar, el contenedor permanecerá sucio y podrá acumular más residuos. 4. Si actúa correctamente, deberá gestionar el recipiente según el procedimiento establecido, utilizando los medios de limpieza disponibles en la actividad. 5. Una vez resuelta la incidencia, pulsa el timbre. Resolución esperada El alumno debe mantener los contenedores limpios y aplicar las medidas de limpieza establecidas por el establecimiento. La actividad no necesita desarrollar aquí una lección completa sobre limpieza y desinfección, ya que el objetivo se centra en reconocer la necesidad de mantener los recipientes de residuos en condiciones higiénicas. Situación 7: Residuos acumulados durante la jornada Contexto Al finalizar una tarea, el alumno observa que se han acumulado restos de alimentos y materiales desechables. El contenedor todavía dispone de espacio, pero la zona de trabajo empieza a estar desordenada. En la parte superior aparecerá el siguiente texto: «La jornada continúa y se han acumulado nuevos residuos. El contenedor todavía tiene espacio, pero debes decidir si conviene dejarlos ahí durante el resto del trabajo o retirarlos ahora». Dinámica detallada 1. El alumno observa el estado de la zona de trabajo y de los contenedores. 2. Debe valorar si los residuos pueden permanecer allí o si es necesario retirarlos. 3. Si decide dejarlos acumulados durante el resto de la jornada, la zona permanecerá desordenada y los residuos seguirán presentes cerca del área de preparación. 4. Si decide actuar, recogerá los residuos y los depositará en el contenedor correspondiente. 5. Si el contenedor está en condiciones de seguir utilizándose, podrá continuar con él. Si está demasiado lleno o sucio, deberá resolver también esa situación. 6. Cuando considere que ha terminado, pulsa el timbre. Resolución esperada El alumno debe retirar los residuos con la frecuencia necesaria para evitar su acumulación en la zona de trabajo. No debe esperar necesariamente a que el contenedor esté lleno: debe observar el estado de la cocina y actuar cuando los residuos puedan interferir con la higiene o con la preparación de alimentos. Cierre de la actividad Al superar las siete situaciones, aparecerá un mensaje final: «Buen trabajo. Durante la jornada has aprendido que gestionar los residuos no consiste únicamente en tirar la basura. También debes utilizar los contenedores adecuados, mantenerlos limpios y en buenas condiciones, retirar los residuos con la frecuencia necesaria y lavarte las manos después de manipularlos. Recuerda que una cocina limpia y organizada ayuda a prevenir contaminaciones y permite trabajar con mayor seguridad». Feedback El feedback aparecerá cuando el alumno pulse el icono del timbre para solicitar la revisión de sus acciones. Si ha cometido un error, recibirá una indicación para reflexionar sobre lo ocurrido y podrá volver a la escena para corregirlo. En el primer intento se priorizarán preguntas o pistas breves. Si el alumno repite el error, recibirá una explicación más explícita de la práctica adecuada y de sus consecuencias. | F41: El feedback Situación 1: Cada residuo en su lugar Si deposita un residuo en un contenedor incorrecto: Primer feedback: «Revisa el residuo que acabas de depositar. ¿Es este el contenedor habilitado para ese tipo de material?». Si necesita más ayuda: «Cada tipo de residuo debe depositarse en el recipiente correspondiente. Comprueba la identificación de los contenedores y coloca el residuo en el lugar adecuado». Si deposita todos los residuos correctamente: «Has identificado los distintos residuos y los has depositado en sus contenedores correspondientes. Así mantienes la zona de trabajo más ordenada y facilitas una gestión adecuada de la basura». Situación 2: El contenedor se está llenando Si continúa utilizando el contenedor hasta que los residuos sobresalen o se derraman: Primer feedback: «El contenedor está cada vez más lleno. ¿Es necesario esperar a que no quepa nada más para retirarlo?». Si necesita más ayuda: «Un contenedor demasiado lleno puede provocar derrames y dificultar su manejo. Retíralo cuando sea necesario y deja disponible un recipiente adecuado para continuar trabajando». Si retira el contenedor a tiempo: «Has detectado que el contenedor necesitaba retirarse antes de llenarse por completo. Anticiparte evita derrames y facilita el trabajo en la cocina». Situación 3: Residuos junto a los alimentos Si continúa trabajando sin retirar los residuos: Primer feedback: «Los residuos siguen junto a la zona de preparación. ¿Qué podría ocurrir si permanecen cerca de los alimentos y de las superficies de trabajo?». Si necesita más ayuda: «Los residuos pueden favorecer la contaminación de los alimentos o de las superficies donde se preparan. Retíralos y mantén despejada la zona antes de continuar». Si retira los residuos correctamente: «Has retirado los restos y los envases de la zona de preparación. Mantener los residuos alejados de los alimentos ayuda a reducir el riesgo de contaminación». Situación 4: Un contenedor sin tapa Si deja abierto el contenedor cuando debería estar cerrado: Primer feedback: «Has revisado el contenedor, pero sigue abierto. ¿Cómo puedes mantener los residuos más protegidos y contenidos?». Si necesita más ayuda: «Los contenedores deben mantenerse limpios y, siempre que sea posible, con tapa. Ciérralo cuando corresponda para evitar que los residuos queden expuestos innecesariamente». Si coloca la tapa correctamente: «Has comprobado el estado del contenedor y lo has dejado cerrado. Recuerda mantener los recipientes en condiciones higiénicas durante toda la jornada». Situación 5: Manipular la basura y volver al trabajo Si vuelve directamente a manipular alimentos sin lavarse las manos: Primer feedback: «Acabas de manipular residuos. ¿Puedes volver directamente a trabajar con alimentos sin realizar ninguna medida de higiene?». Si necesita más ayuda: «Al manipular basura, las manos pueden contaminarse. Debes lavártelas con agua y jabón antes de volver a trabajar con alimentos». Si se lava correctamente las manos: «Te has lavado las manos después de manipular residuos. Así reduces el riesgo de transferir suciedad y contaminantes a los alimentos y utensilios». Situación 6: Contenedor sucio Si sigue utilizando el contenedor sin actuar: Primer feedback: «El recipiente presenta suciedad acumulada. ¿Es adecuado mantenerlo en esas condiciones durante toda la jornada?». Si necesita más ayuda: «Los contenedores de residuos también deben mantenerse limpios. Aplica las medidas de limpieza establecidas para evitar que la suciedad se acumule». Si gestiona correctamente la limpieza del recipiente: «Has detectado la suciedad y has actuado para mantener el contenedor en condiciones higiénicas. Recuerda que la limpieza de los recipientes forma parte de la gestión correcta de los residuos». Situación 7: Residuos acumulados durante la jornada Si deja los residuos acumulados porque el contenedor todavía tiene espacio: Primer feedback: «El contenedor no está lleno, pero los residuos se han acumulado en la zona de trabajo. ¿Es necesario esperar a llenarlo para retirarlos?». Si necesita más ayuda: «Los residuos deben retirarse con la frecuencia necesaria para evitar que se acumulen e interfieran con la higiene de la cocina. Recógelos y deposítalos en el lugar correspondiente». Si retira los residuos y deja la zona despejada: «Has retirado los residuos sin esperar a que el contenedor estuviera lleno. Observar el estado de la zona y actuar a tiempo ayuda a mantener unas condiciones higiénicas durante toda la jornada». | G41: ='Cont-Obj'!E:E -> 5.5 Prevención y control de plagas
A42: ='Cont-Obj'!A:A -> Módulo 5. Limpieza, desinfección y mantenimiento | B42: ='Cont-Obj'!B:B -> O5.9 Determinar cuándo el aceite de fritura debe mantenerse, controlarse o sustituirse de acuerdo con sus condiciones y los procedimientos del establecimiento. | C42: ='Cont-Obj'!C:C -> 32 | G42: ='Cont-Obj'!E:E -> 5.6 Mantenimiento del aceite de fritura
A43: ='Cont-Obj'!A:A -> Módulo 6. Gestión segura de los alérgenos | B43: ='Cont-Obj'!B:B -> O6.1 Diferenciar entre alergia e intolerancia alimentaria. | C43: ='Cont-Obj'!C:C -> 33 | G43: ='Cont-Obj'!E:E -> 6.1 ¿Qué son las alergias y las intolerancias alimentarias?
A44: ='Cont-Obj'!A:A -> Módulo 6. Gestión segura de los alérgenos | B44: ='Cont-Obj'!B:B -> O6.2 Identificar los 14 alérgenos de declaración obligatoria. | C44: ='Cont-Obj'!C:C -> 34 | G44: ='Cont-Obj'!E:E -> 6.2 Los 14 alérgenos de declaración obligatoria
A45: ='Cont-Obj'!A:A -> Módulo 6. Gestión segura de los alérgenos | B45: ='Cont-Obj'!B:B -> O6.3 Reconocer cuáles son las fuentes de información establecidas para comprobar la presencia de alérgenos en un plato. | C45: ='Cont-Obj'!C:C -> 35 | G45: ='Cont-Obj'!E:E -> 6.3 Informar correctamente al cliente
A46: ='Cont-Obj'!A:A -> Módulo 6. Gestión segura de los alérgenos | B46: ='Cont-Obj'!B:B -> O6.5 Determinar cuándo debe consultar al responsable antes de responder a una pregunta relacionada con alérgenos. | C46: ='Cont-Obj'!C:C | G46: ='Cont-Obj'!E:E -> 6.3 Informar correctamente al cliente
A47: ='Cont-Obj'!A:A -> Módulo 6. Gestión segura de los alérgenos | B47: ='Cont-Obj'!B:B -> INCLUIR OBJETIVO SOBRE CONTAMINACIÓN CRUZADA RELACIONADA CON ALÉRGENOS Reconocer las situaciones durante la preparación y el servicio en las que puede existir un riesgo relacionado con los alérgenos. | C47: ='Cont-Obj'!C:C | G47: ='Cont-Obj'!E:E
A48: ='Cont-Obj'!A:A -> Módulo 7. La seguridad alimentaria en el establecimiento | B48: ='Cont-Obj'!B:B -> O7.1 Comprender la importancia del trabajo coordinado de todas las personas del establecimiento para garantizar la seguridad alimentaria. | C48: ='Cont-Obj'!C:C -> 36 | G48: ='Cont-Obj'!E:E -> 7.1 La seguridad alimentaria es un trabajo en equipo
A49: ='Cont-Obj'!A:A -> Módulo 7. La seguridad alimentaria en el establecimiento | B49: ='Cont-Obj'!B:B -> O7.2 Conocer la finalidad del sistema APPCC y el papel del manipulador en su aplicación. | C49: ='Cont-Obj'!C:C -> 36 | G49: ='Cont-Obj'!E:E -> 7.2 ¿Qué es el APPCC?
A50: ='Cont-Obj'!A:A -> Módulo 7. La seguridad alimentaria en el establecimiento | B50: ='Cont-Obj'!B:B -> O7.3 Identificar la función de la trazabilidad y su utilidad para identificar el recorrido de los alimentos. | C50: ='Cont-Obj'!C:C -> 37 | G50: ='Cont-Obj'!E:E -> 7.3 La trazabilidad: conocer el recorrido de un alimento
A51: ='Cont-Obj'!A:A -> Módulo 7. La seguridad alimentaria en el establecimiento | B51: ='Cont-Obj'!B:B -> O7.4 Cumplimentar correctamente los registros relacionados con las tareas de seguridad alimentaria siguiendo los procedimientos establecidos. | C51: ='Cont-Obj'!C:C -> 38 (texto) | G51: ='Cont-Obj'!E:E -> 7.4 La importancia de los registros
A52: ='Cont-Obj'!A:A -> Módulo 7. La seguridad alimentaria en el establecimiento | B52: ='Cont-Obj'!B:B -> O7.4 Cumplimentar correctamente los registros relacionados con las tareas de seguridad alimentaria siguiendo los procedimientos establecidos. | C52: ='Cont-Obj'!C:C -> 39 | G52: ='Cont-Obj'!E:E -> 7.4 La importancia de los registros
A53: ='Cont-Obj'!A:A -> Módulo 7. La seguridad alimentaria en el establecimiento
A54: ='Cont-Obj'!A:A -> Módulo 7. La seguridad alimentaria en el establecimiento
A55: ='Cont-Obj'!A:A
A56: ='Cont-Obj'!A:A
A57: ='Cont-Obj'!A:A
A58: ='Cont-Obj'!A:A
A59: ='Cont-Obj'!A:A
A60: ='Cont-Obj'!A:A
A61: ='Cont-Obj'!A:A
A62: ='Cont-Obj'!A:A
A63: ='Cont-Obj'!A:A
A64: ='Cont-Obj'!A:A
... A162: ='Cont-Obj'!A:A

Sheet Cont-Obj
A1: MÓDULOS | B1: OBJETIVOS | C1: NUM ACT | D1: ACTIVIDAD | E1: CONTENIDOS
A2: Módulo 1. La seguridad alimentaria empieza contigo | B2: O1.1 Conocer la definición de manipulador de alimentos | C2: 1 | D2: Introducción y actividad de lectura | E2: 1.1 ¿Qué es un manipulador de alimentos?
A3: Módulo 1. La seguridad alimentaria empieza contigo | B3: O1.2 Identificar qué puestos de trabajo implican manipulación de alimentos dentro de la cadena alimentaria. | C3: 2 | D3: ¿Quién es manipulador de alimentos? | E3: 1.1 ¿Qué es un manipulador de alimentos?
A4: Módulo 1. La seguridad alimentaria empieza contigo | B4: O1.3 Comprender la importancia del papel del manipulador de alimentos en la seguridad y salud de los consumidores. | C4: 3 | D4: Cámaras de seguridad: del manipulador al consumidor. | E4: 1.2 ¿Por qué es tan importante tu trabajo?
A5: Módulo 1. La seguridad alimentaria empieza contigo | B5: O1.4 Reconocer las principales consecuencias que puede tener una manipulación incorrecta de los alimentos para los consumidores, el establecimiento y el propio manipulador. | C5: 4 | D5: ¿A quién afecta? | E5: 1.3 ¿Qué puede ocurrir si no manipulamos bien los alimentos?
A6: Módulo 1. La seguridad alimentaria empieza contigo | B6: O1.5 Identificar las reglas básicas de seguridad alimentaria durante las tareas de manipulación. | C6: 5 | D6: Detectives de la cocina. | E6: 1.4 Las reglas básicas para trabajar con seguridad
A7: Módulo 1. La seguridad alimentaria empieza contigo | B7: O7.1 Comprender la importancia del trabajo coordinado de todas las personas del establecimiento para garantizar la seguridad alimentaria. | E7: 1.5 Tu responsabilidad como manipulador de alimentos
A8: Módulo 2. Higiene personal del manipulador | B8: O2.1 Conocer las condiciones de salud que pueden afectar a la seguridad de los alimentos. | C8: 6 | D8: Actividad de lectura (la higiene empieza por ti) | E8: 2.1 La higiene empieza por ti
A9: Módulo 2. Higiene personal del manipulador | B9: O2.1 Conocer las condiciones de salud que pueden afectar a la seguridad de los alimentos. | C9: 7 | D9: Actividad de lectura (tu estado de salud importa) | E9: 2.1 La higiene empieza por ti
A10: Módulo 2. Higiene personal del manipulador | B10: O2.2 Aplicar correctamente las normas de higiene personal y utilización del uniforme durante la manipulación de alimentos. | C10: 8 | D10: Antes de comenzar, revisa tu uniforme e higiene. | E10: 2.2 El uniforme y la higiene personal
A11: Módulo 2. Higiene personal del manipulador | B11: O2.3 Identificar cómo las manos, el cabello, la barba, las uñas, las joyas y la ropa pueden convertirse en fuentes de contaminación. | C11: 8 | D11: Antes de comenzar, revisa tu uniforme e higiene. | E11: 2.3 Cabello, barba, uñas y joyas
A12: Módulo 2. Higiene personal del manipulador | B12: O2.4 Ejecutar correctamente el lavado y secado de manos. | C12: 9 | D12: Manos a la obra: el lavado perfecto. | E12: 2.4 El lavado de manos
A13: Módulo 2. Higiene personal del manipulador | B13: O2.5 Identificar en qué situaciones deben ser lavadas las manos | C13: 10 | D13: ¿Te lavarías las manos? | E13: 2.4 El lavado de manos
A14: Módulo 2. Higiene personal del manipulador | B14: O2.6 Determinar cuándo es necesario cambiar los guantes y cómo utilizarlos de forma segura. | C14: 11 | D14: Actividad de lectura (heridas y cortes) | E14: 2.5 El uso correcto de los guantes
A15: Módulo 2. Higiene personal del manipulador | B15: O2.7 Aplicar el procedimiento establecido ante heridas y lesiones durante la manipulación de alimentos. | C15: 12 | D15: Heridas a raya: protege, decide y trabaja seguro. | E15: 2.6 Heridas y cortes
A16: Módulo 3. Manipulación segura de los alimentos | B16: O3.1 Identificar qué es la contaminación alimentaria y reconocer cómo puede producirse a lo largo de las distintas etapas de la cadena alimentaria. | C16: 13 | D16: Actividad de lectura (¿qué es la contaminación alimentaria?) | E16: 3.1 ¿Qué es la contaminación alimentaria?
A17: Módulo 3. Manipulación segura de los alimentos | B17: O3.2 Distinguir los diferentes tipos de contaminación alimentaria: biológica, física y química. | C17: 14 | D17: Actividad de lectura (¿cómo pueden contaminarse los alimentos?) | E17: 3.2 ¿Cómo pueden contaminarse los alimentos?
A18: Módulo 3. Manipulación segura de los alimentos | B18: O3.3 Identificar las principales fuentes y vías de contaminación de los alimentos durante su manipulación. | C18: 15 | D18: Tras la barra. | E18: 3.2 ¿Cómo pueden contaminarse los alimentos?
A19: Módulo 3. Manipulación segura de los alimentos | B19: O3.4 Comprender cómo se produce la contaminación cruzada. | C19: 16 | D19: Actividad de lectura (por definir) | E19: 3.3 La contaminación cruzada
... A28: Módulo 4. Conservación y control de temperaturas | B28: O4.5 Aplicar correctamente los procedimientos de cocinado, enfriamiento y recalentamiento de los alimentos para mantener su seguridad durante su preparación y conservación. | C28: 23 | D28: Texto | E28: 4.4 Cocinado, enfriamiento y recalentamiento
A29: Módulo 4. Conservación y control de temperaturas | B29: O4.5 Aplicar correctamente los procedimientos de cocinado, enfriamiento y recalentamiento de los alimentos para mantener su seguridad durante su preparación y conservación. | C29: 24 | E29: 4.4 Cocinado, enfriamiento y recalentamiento
A30: Módulo 4. Conservación y control de temperaturas | B30: O4.6 Mantener los alimentos en condiciones adecuadas de temperatura durante su conservación y servicio. | E30: 4.5 Mantenimiento de los alimentos y servicio
A31: Módulo 4. Conservación y control de temperaturas | B31: O4.7 Organizar correctamente los alimentos en cámaras y almacenes para favorecer su conservación y evitar contaminaciones. | C31: 25 | D31: Cada cosa en su lugar | E31: 4.6 Almacenamiento seguro y organización de cámaras
B32: O4.8 Diferenciar entre fecha de caducidad y fecha de consumo preferente. | C32: 26 | D32: Texto (explicación de fecha de caducidad, fecha de consumo preferente y FIFO)
A33: Módulo 4. Conservación y control de temperaturas | B33: O4.8 Aplicar sistemas adecuados de rotación de productos y control de fechas. | C33: 27 | E33: 4.7 Rotación y control de fechas
A34: Módulo 5. Limpieza, desinfección y mantenimiento | B34: O5.1 Conocer la importancia de la limpieza y la desinfección para prevenir riesgos alimentarios. | C34: 28 | D34: Texto | E34: 5.1 Limpieza y desinfección: una parte esencial de la seguridad alimentaria
A35: Módulo 5. Limpieza, desinfección y mantenimiento | B35: O5.2 Diferenciar entre limpiar y desinfectar | C35: 29 | E35: 5.2 ¿Limpiar o desinfectar?
A36: Módulo 5. Limpieza, desinfección y mantenimiento | B36: O5.3 Comprender el orden adecuado en el que debe realizarse la limpieza y la desinfección | C36: 29 | E36: 5.2 ¿Limpiar o desinfectar?
A37: Módulo 5. Limpieza, desinfección y mantenimiento | B37: O5.4 Aplicar correctamente las normas de seguridad durante el uso y almacenamiento de productos químicos. | C37: 29 | E37: 5.3 Productos de limpieza y desinfección
A38: Módulo 5. Limpieza, desinfección y mantenimiento | B38: O5.5 Seleccionar los productos de limpieza y desinfección adecuados siguiendo las instrucciones y procedimientos establecidos. | C38: 29 | E38: 5.3 Productos de limpieza y desinfección
A39: Módulo 5. Limpieza, desinfección y mantenimiento | B39: O5.6 Gestionar los residuos de forma que se reduzcan los riesgos de contaminación y aparición de plagas. | C39: 30 | D39: Durante la jornada de trabajo, en la cocina se van acumulando distintos residuos. Tu tarea es mantener la zona de trabajo limpia y gestionar la basura correctamente. En diferentes momentos aparecerán situaciones relacionadas con los residuos. Tendrás que decidir qué acción debes realizar | E39: 5.4 Gestión de residuos
A40: Módulo 5. Limpieza, desinfección y mantenimiento | B40: O5.7 Identificar señales de presencia de plagas | C40: 31 | D40: Recorrerás diferentes zonas del establecimiento y encontrarás situaciones correctas, situaciones que favorecen la aparición de plagas y posibles indicios de que ya existe una plaga. En cada situación tendrás que decidir qué hacer. | E40: 5.5 Prevención y control de plagas
A41: Módulo 5. Limpieza, desinfección y mantenimiento | B41: O5.8 Conocer que las incidencias de presencia de plagas se debe comunicar siguiendo el procedimiento establecido. | C41: 31 | E41: 5.5 Prevención y control de plagas
A42: Módulo 5. Limpieza, desinfección y mantenimiento | B42: O5.9 Determinar cuándo el aceite de fritura debe mantenerse, controlarse o sustituirse de acuerdo con sus condiciones y los procedimientos del establecimiento. | C42: 32 | D42: A lo largo de la actividad irán apareciendo diferentes situaciones relacionadas con el estado del aceite. Tendrás que observar la freidora, retirar los restos de alimentos cuando sea necesario y decidir si puedes continuar utilizando el aceite o si debe sustituirse. | E42: 5.6 Mantenimiento del aceite de fritura
A43: Módulo 6. Gestión segura de los alérgenos | B43: O6.1 Diferenciar entre alergia e intolerancia alimentaria. | C43: 33 | D43: Texto: No todas las personas reaccionan de la misma forma ante los alimentos. Mientras que la mayoría puede consumirlos sin problemas, algunas pueden sufrir reacciones adversas debido a una alergia o una intolerancia alimentaria. Una alergia alimentaria implica una reacción del sistema inmunitario y, en algunos casos, incluso una pequeña cantidad del alimento puede provocar una reacción grave. Las intolerancias no implican al sistema inmunitario, pero también pueden causar molestias y afectar a la salud. Por este motivo, es importante conocer los ingredientes que contienen los alimentos y prestar especial atención a los alérgenos de declaración obligatoria. Como manipulador de alimentos, no necesitas diagnosticar una alergia o intolerancia, pero sí debes conocer y aplicar las medidas necesarias para evitar riesgos. | E43: 6.1 ¿Qué son las alergias y las intolerancias alimentarias?
A44: Módulo 6. Gestión segura de los alérgenos | B44: O6.2 Identificar los 14 alérgenos de declaración obligatoria. | C44: 34 | D44: Estás preparando varios platos de la carta y necesitas comprobar qué alérgenos pueden estar presentes en cada uno. Tu tarea será identificar cuáles de esos ingredientes pertenecen a los 14 grupos de alérgenos de declaración obligatoria. | E44: 6.2 Los 14 alérgenos de declaración obligatoria
A45: Módulo 6. Gestión segura de los alérgenos | B45: O6.3 Reconocer cuáles son las fuentes de información establecidas para comprobar la presencia de alérgenos en un plato. | C45: 35 | D45: texto | E45: 6.3 Informar correctamente al cliente
A46: Módulo 6. Gestión segura de los alérgenos | B46: O6.5 Determinar cuándo debe consultar al responsable antes de responder a una pregunta relacionada con alérgenos. | E46: 6.3 Informar correctamente al cliente
A47: Módulo 6. Gestión segura de los alérgenos | B47: INCLUIR OBJETIVO SOBRE CONTAMINACIÓN CRUZADA RELACIONADA CON ALÉRGENOS Reconocer las situaciones durante la preparación y el servicio en las que puede existir un riesgo relacionado con los alérgenos.
A48: Módulo 7. La seguridad alimentaria en el establecimiento | B48: O7.1 Comprender la importancia del trabajo coordinado de todas las personas del establecimiento para garantizar la seguridad alimentaria. | C48: 36 | D48: Texto | E48: 7.1 La seguridad alimentaria es un trabajo en equipo
A49: Módulo 7. La seguridad alimentaria en el establecimiento | B49: O7.2 Conocer la finalidad del sistema APPCC y el papel del manipulador en su aplicación. | C49: 36 | D49: Texto | E49: 7.2 ¿Qué es el APPCC?
A50: Módulo 7. La seguridad alimentaria en el establecimiento | B50: O7.3 Identificar la función de la trazabilidad y su utilidad para identificar el recorrido de los alimentos. | C50: 37 | E50: 7.3 La trazabilidad: conocer el recorrido de un alimento
A51: Módulo 7. La seguridad alimentaria en el establecimiento | B51: O7.4 Cumplimentar correctamente los registros relacionados con las tareas de seguridad alimentaria siguiendo los procedimientos establecidos. | C51: 38 (texto) | D51: Los registros de seguridad alimentaria permiten dejar constancia de los controles y procedimientos que se realizan en el establecimiento. Mantener esta información correctamente cumplimentada ayuda a comprobar que las medidas de seguridad se están aplicando y facilita detectar posibles incidencias. Además, la trazabilidad permite conocer el recorrido que ha seguido un alimento desde su origen hasta su consumo. Para poder realizar este seguimiento, es importante conservar de forma adecuada la información necesaria sobre los productos, proveedores, lotes y controles realizados. | E51: 7.4 La importancia de los registros
A52: Módulo 7. La seguridad alimentaria en el establecimiento | B52: O7.4 Cumplimentar correctamente los registros relacionados con las tareas de seguridad alimentaria siguiendo los procedimientos establecidos. | C52: 39 | D52: Tendrás que revisar varios registros y comprobar si están completamente cumplimentados o si falta algún dato importante | E52: 7.4 La importancia de los registros
A53: Módulo 7. La seguridad alimentaria en el establecimiento | B53: O7.5 Identificar incidencias que puedan afectar a la seguridad de los alimentos. | C53: 40 | D53: Se presentarán una serie de incidencias y debes decidir si avisar al responsable del establecimiento o no. | E53: 7.5 Actuación ante incidencias
